Workbook

Sheet Portada
A1: Sistema DM — Ejemplo de Presupuesto (golden test)
A2: v1.7 · 1 de agosto de 2026 · caso de referencia: 100 t, clase 40 HH/t, conexión apernada
A4: Leyenda de alcance del precio (regla de emisión)
A5: Este es el mejor precio calculable bajo las condiciones e información actuales de la compañía (planta, inventario, costos y precios confirmados a la fecha) y lo que exige la oferta. No es predicción del precio ganador del mercado; la decisión final de margen y la firma de la oferta son de la dirección.
A9: Convenciones de color
A10: Azul: entrada / palanca de escenario
A11: Negro: fórmula
A12: Verde: liga a otra hoja
A13: Amarillo: supuesto clave o celda a llenar
A15: Parámetros registrados del caso
A16: Una sola familia/clase (40 HH/t) → subproyectos no aplica; alerta_interferencia_familias = no_aplica.
A17: Crecimiento "Más 6%" FIJADO en 6% (defecto de la fase RSS ámbar sería 10%); justificación: caso de referencia.
... A21: Documento rector: claude/instrucciones-sistema-dm.md (v1.7). Orden de conflictos: rector → kit → Excel → narrativa.

Sheet Parametros_Version
A1: Versión de parámetros v2026.1
A2: Invariante 16: los parámetros nunca se recalibran solos; todo cambio genera nueva versión aprobada por dirección.
A4: Eje de complejidad (HH/t) | B4: 24 | C4: 40 | D4: 60 | E4: Clase 90 en fila siguiente; VSM E4
A5: clase alta | B5: 90
A6: Crecimiento por fase RSS (verde/ámbar/rojo) | B6: 0.06 | C6: 0.1 | D6: 0.15
A7: Tolerancia de cierre por rubro (inv. 16) | B7: 0.05
A9: Costo empresa propio ($/HH) | B9: 122.79
A10: Subcontrato all-in ($/HH) | B10: 164.85
A11: Prima de sobretiempo | B11: 0.5
A12: Tarifa all-in resolución de déficit ($/HH) | B12: 158.175
A13: Capacidad HH libres de habilitado (HH/sem) | B13: 600

Sheet E1_Ficha
A1: E1 — Ficha del proyecto
A4: Proyecto | B4: Nave industrial — caso de referencia
A5: Cliente | B5: Cliente del concurso
A6: Ubicación | B6: Parque industrial (nacional)
A7: Peso de planos (t) | B7: 100
A8: Clase de complejidad (HH/t) | B8: 40
A9: Conexión principal | B9: Apernada A325
A10: Fase RSS declarada | B10: Ámbar
A11: Plazo de montaje | B11: 5 semanas (plan del cliente, E6)

Sheet E2_TakeOff
A1: E2 — Take-off (IFC)
A2: Peso único AISC 303-22 §9.2 (invariante 1) y doble chequeo (invariante 4).
A4: Concepto | B4: Valor | C4: Unidad | D4: Nota
A5: Peso de planos | B5: 100 | C5: t | D5: Entrada del take-off IFC
A6: Factor facturable AISC 303-22 §9.2 | B6: 1.137
A7: Peso facturable | B7: =E2_TakeOff!$B$5*E2_TakeOff!$B$6 -> 113.7 | C7: t
A8: Desperdicio de la clase | B8: 0.0664028
A9: Acero a comprar | B9: =E2_TakeOff!$B$7*(1+E2_TakeOff!$B$8) -> 121.25 | C9: t
A10: Factor global (comprar/planos) | B10: =E2_TakeOff!$B$9/E2_TakeOff!$B$5 -> 1.2125
A11: Peso reconstruido (chequeo) | B11: 113.68
A12: Doble chequeo del peso | B12: =IF(ABS(E2_TakeOff!$B$11-E2_TakeOff!$B$7)/E2_TakeOff!$B$7<=0.005,"OK","DETENER EMISIÓN") -> OK
A14: EXCLUSIONES EXPLÍCITAS (invariante 5)
A15: Escaleras — EXCLUIDAS (partida con leyenda, nunca cero silencioso)
A16: Pernos de anclaje F1554 — EXCLUIDOS
A17: Nelson studs — EXCLUIDOS

Sheet E3_Precios
A1: E3 — Precios vigentes de materia prima
A2: Entrada crítica con vigencia (invariante 8).
A4: Material | B4: Precio $/kg | C4: Fuente | D4: Fecha | E4: Vigencia (días) | F4: Estado
A5: Perfil W (A992) | B5: 24.8 | C5: Cotización molino | D5: 2026-07-21 | E5: 9 | F5: =IF(E5>0,"VIGENTE","BLOQUEADO") -> VIGENTE
A6: Placa (A572-50) | B6: 26.1 | C6: Distribuidor | D6: 2026-07-24 | E6: 12 | F6: =IF(E6>0,"VIGENTE","BLOQUEADO") -> VIGENTE
A7: HSS (A500-C) | B7: 28.35 | C7: Distribuidor | D7: 2026-07-18 | E7: 6 | F7: =IF(E7>0,"VIGENTE","BLOQUEADO") -> VIGENTE
A8: Soldadura FCAW E71T-1 | B8: 118 | C8: Proveedor | D8: 2026-07-15 | E8: 30 | F8: =IF(E8>0,"VIGENTE","BLOQUEADO") -> VIGENTE
A9: Precio promedio ponderado del caso | B9: 25
A11: La confirmación explícita de estos precios antes de emitir vive en la hoja Bitacora_Precios (invariante 8, v1.7).

Sheet E4_Planta_VSM
A1: E4 — Planta / VSM
A4: HH/t de la clase del proyecto | B4: 40 | C4: Eje único de complejidad (invariante 2)
A5: Velocidad base de montaje (t/sem) | B5: 15 | C5: Capacidad propia
A6: Velocidad con sobretiempo (t/sem) | B6: 24 | C6: Base + OT prima 50%
A7: Cuello de botella | B7: Soldadura FCAW | C7: Según VSM
A8: Ahorro Lean verificable (HH/t) | B8: 8.4% | C8: Ver hoja LEAN

Sheet E5_Financieros
A1: E5 — Datos financieros (costo empresa)
A2: Invariante 15: $/HH desde datos reales; todo ANTES de impuestos.
A4: Costo empresa propio ($/HH) | B4: =Parametros_Version!$B$9 -> 122.79 | C4: Nómina + prestaciones + sindicato/CCT; tolerancia 2% vs contabilidad
A5: Subcontrato all-in ($/HH) | B5: =Parametros_Version!$B$10 -> 164.85 | C5: Incluye supervisión y consumibles
A6: Cargas de planta ($/HH equivalente) | B6: 99.61 | C6: Cargas fijas prorrateadas
A7: Overhead disponible ($/HH equivalente) | B7: 115.45 | C7: Overhead que absorbe el programa
A8: Chequeo: overhead cubre cargas | B8: =IF($B$6<$B$7,"CUBIERTAS","ALERTA") -> CUBIERTAS

Sheet E6_Especificaciones
A1: E6 — Especificaciones, formato y plan de montaje
A2: Invariante 10: el concurso RIGE sobre la norma. Invariante 11: el plan de montaje es ENTRADA.
A4: Registro de desviaciones concurso vs norma
A5: Concepto | B5: Norma | C5: Concurso | D5: Rige | E5: Impacto $
A6: NDT en soldadura de taller | B6: Visual 100% | C6: UT 20% adicional | D6: Concurso | E6: 48200
A7: Sistema de recubrimiento | B7: SSPC-SP6 + 1 capa | C7: SP10 + 2 capas | D7: Concurso | E7: 121400
A8: Tolerancia de contraflecha | B8: AISC 303 estándar | C8: Estrecha (75%) | D8: Concurso | E8: 18600
A9: Costo de desviaciones (entra al presupuesto) | E9: =SUM(E6:E8) -> 188200
A11: Plan de montaje del cliente (t/sem exigidas)
A12: Semana | B12: 1 | C12: 2 | D12: 3 | E12: 4 | F12: 5
A13: t/sem plan | B13: 22 | C13: 38 | D13: 24 | E13: 21 | F13: 10

Sheet E7_Carga_Inventario
A1: E7 — Carga de planta, inventario y cierres
A2: Invariante 13 (inventario primero) e invariante 16 (registro de cierres).
A4: Carga de proyectos EN CURSO (HH/sem)
A5: Proyecto | B5: Sem 1 | C5: Sem 2 | D5: Sem 3 | E5: Sem 4 | F5: Sem 5
A6: San Antonio Abad | B6: 180 | C6: 210 | D6: 160 | E6: 190 | F6: 160
A7: Chabacano | B7: 140 | C7: 160 | D7: 120 | E7: 150 | F7: 100
A8: World Park El Salto | B8: 80 | C8: 96 | D8: 80 | E8: 98 | F8: 100
A9: Total en curso | B9: =SUM(B6:B8) -> 400 | C9: =SUM(C6:C8) -> 466 | D9: =SUM(D6:D8) -> 360 | E9: =SUM(E6:E8) -> 438 | F9: =SUM(F6:F8) -> 360
A11: Inventario de materia prima (t)
A12: Concepto | B12: Disponible | C12: Asignado | D12: LIBRE
A13: Acero estructural | B13: 61 | C13: 27 | D13: =B13-C13 -> 34
A14: Libre aplicable al proyecto: 34.00 t (61−27). Préstamos entre contratos: siempre registrados.
A16: Registro de cierres de proyecto (inv. 16) | B16: Ver hoja Cierre_Proyecto

Sheet S1_Boom
A1: S1 — Boom (explosión de materiales)
A4: Familia de perfil | B4: Facturable (t) | C4: Participación
A5: Perfiles W | B5: 68.2 | C5: =B5/$B$9 -> 0.5998241
A6: Placa | B6: 22.75 | C6: =B6/$B$9 -> 0.20008795
A7: HSS | B7: 12.4 | C7: =B7/$B$9 -> 0.10905893
A8: Conexiones y misceláneos | B8: 10.35 | C8: =B8/$B$9 -> 0.091029024
A9: Total facturable | B9: =SUM(B5:B8) -> 113.7
A10: Chequeo vs E2 | B10: =IF(ABS(B9-E2_TakeOff!$B$7)<0.01,"OK","REVISAR") -> OK

Sheet S2_APU_AISC
A1: S2 — APU método AISC (composición única, invariante 6)
A4: Partida | B4: Importe | C4: Base
A5: Material de acero | B5: =E2_TakeOff!$B$9*1000*E3_Precios!$B$9 -> 3031250 | C5: 121.25 t × $25.00/kg (E2 × E3)
A6: Consumibles de soldadura y abrasivos | B6: 187450
A7: MO fabricación (propia) | B7: =E2_TakeOff!$B$5*E4_Planta_VSM!$B$4*E5_Financieros!$B$4 -> 491160 | C7: 4,000 HH × 122.79 $/HH (E2 × E4 × E5)
A8: MO subcontrato pico de velocidad | B8: =S11_Velocidad!$B$8*E5_Financieros!$B$5 -> 92316 | C8: 560 HH × 164.85 $/HH (S11 × E5)
A9: Recubrimiento SSPC (incl. desviación concurso) | B9: 386580
A10: Fletes y maniobras | B10: 248900
A11: Indirectos y overhead de planta | B11: 585000
A12: Supervisión, QC y dossier | B12: 176300
A13: Margen | B13: 778397
A14: APU AISC — TOTAL | B14: =SUM(B5:B13) -> 5977353
A15: $/kg sobre facturable | B15: =S2_APU_AISC!$B$14/(E2_TakeOff!$B$7*1000) -> 52.571266

Sheet S3_Mas6
A1: S3 — Método por partidas "Más 6%"
A2: Invariante 6 (v1.7): % de crecimiento atado al semáforo RSS; aquí FIJADO en 6% (registrado).
A4: Fase RSS vigente | B4: Ámbar | C4: Ver S10_Checklist_RSS; defecto de la fase: 10%
A5: % de crecimiento APLICADO | B5: 0.06
A6: Peso propuesto (planos + crecimiento) | B6: =E2_TakeOff!$B$5*(1+S3_Mas6!$B$5) -> 106
A8: Partida por perfil (doble MO prefab+fab) | B8: Importe
A9: Perfiles W | B9: 4988000
A10: Placa | B10: 1672300
A11: HSS | B11: 793900
A12: Misceláneos | B12: 339428
A13: Subtotal por perfil | B13: =SUM(B9:B12) -> 7793628
A14: Partidas generales | B14: 121305
A15: Más 6% — TOTAL | B15: =B13+B14 -> 7914933
A16: A margen comparable (21%) | B16: 6011342
A17: Reconciliación vs APU | B17: =S3_Mas6!$B$16/S2_APU_AISC!$B$14-1 -> 0.0056863032
A18: Criterio (<1%) | B18: =IF(ABS(S3_Mas6!$B$16/S2_APU_AISC!$B$14-1)<0.01,"RECONCILIA","REVISAR") -> RECONCILIA

Sheet S11_Velocidad
A1: S11 — Doble chequeo de velocidad (invariante 12)
A4: Chequeo 1: velocidad del montaje
A5: Pico del plan de montaje (t/sem) | B5: =E6_Especificaciones!$C$13 -> 38
A6: Velocidad base / con OT (t/sem) | B6: =E4_Planta_VSM!$B$5&" / "&E4_Planta_VSM!$B$6 -> 15 / 24
A7: Excedente sobre OT (t/sem) | B7: =MAX(0,E6_Especificaciones!$C$13-E4_Planta_VSM!$B$6) -> 14
A8: alerta_subcontrato (HH) | B8: =B7*E4_Planta_VSM!$B$4 -> 560
A9: Chequeo 2: planta vs punto de equilibrio
A10: Volumen total de planta (t/mes) | B10: 318
A11: Punto de equilibrio (t/mes) | B11: 490
A12: Equilibrio con Lean (t/mes) | B12: 368
A13: Déficit vs equilibrio / vs Lean (t) | B13: =(B11-B10)&" / "&(B12-B10) -> 172 / 50
A14: advertencia_bajo_equilibrio | B14: =IF(B10<B11,"ACTIVA — NUNCA SE SUPRIME","no aplica") -> ACTIVA — NUNCA SE SUPRIME

Sheet S4_Opciones
A1: S4 — Tres opciones de oferta
A2: Difieren en supuestos, no en fórmula (invariante 6).
A4: Opción | B4: Precio | C4: Supuesto diferencial
A5: Opción 1 — Base | B5: =S6_Financiero!$B$7 -> 6183408 | C5: Programa del plan; déficit resuelto según S12 (B*)
A6: Opción 2 — Programa garantizado | B6: =B5+S12_Programa!$B$20 -> 6247556 | C6: Incluye el costo de optimización B* dentro del precio
A7: Opción 3 — Grúa resuelta | B7: =B5+S8_Secuencia_Grua!$C$9 -> 6259408 | C7: Incluye partir 2 piezas críticas ($76,000, valida EOR)

Sheet S5_Flujo
A1: S5 — Flujo de caja del programa
A4: Concepto | B4: Mes 0 | C4: Mes 1 | D4: Mes 2 | E4: Mes 3 | F4: Mes 4 | G4: Total
A5: Cobros (anticipo 30% + estimaciones) | B5: 1855022 | C5: 0 | D5: 1546000 | E5: 1546000 | F5: 1236386 | G5: =SUM(B5:F5) -> 6183408
A6: Pagos (acero, MO, indirectos) | B6: -1210000 | C6: -1520000 | D6: -1430000 | E6: -1050000 | F6: -767353 | G6: =SUM(B6:F6) -> -5977353
A7: Flujo neto | B7: =B5+B6 -> 645022 | C7: =C5+C6 -> -1520000 | D7: =D5+D6 -> 116000 | E7: =E5+E6 -> 496000 | F7: =F5+F6 -> 469033 | G7: =SUM(B7:F7) -> 206055
A9: Costo financiero del programa | B9: 206054

Sheet S6_Financiero
A1: S6 — Capítulo financiero y precio de licitación
A4: APU AISC | B4: =S2_APU_AISC!$B$14 -> 5977353
A5: Capítulo financiero | B5: =S5_Flujo!$B$9 -> 206054
A6: Ajuste de redondeo del caso | B6: 1
A7: PRECIO DE LICITACIÓN | B7: =B4+B5+B6 -> 6183408
A8: $/kg de licitación | B8: =S6_Financiero!$B$7/(E2_TakeOff!$B$7*1000) -> 54.383535
A9: Compuerta de emisión (invariante 8 v1.7) | B9: =Bitacora_Precios!$B$11 -> EMISIÓN HABILITADA
A11: LEYENDA DE ALCANCE: Este es el mejor precio calculable bajo las condiciones e información actuales de la compañía (planta, inventario, costos y precios confirmados a la fecha) y lo que exige la oferta. No es predicción del precio ganador; margen final y firma son de la dirección.

Sheet S7_Requisicion
A1: S7 — Requisición neta (inventario primero, invariante 13)
A4: Acero a comprar (E2) | B4: =E2_TakeOff!$B$9 -> 121.25
A5: Redondeo comercial a largos | B5: 0.3
A6: Requisición bruta | B6: =B4+B5 -> 121.55
A7: Inventario LIBRE aplicable (E7) | B7: =E7_Carga_Inventario!$D$13 -> 34
A8: NETO A COMPRAR | B8: =B6-B7 -> 87.549998
A9: Préstamos entre contratos: siempre registrados en E7.

Sheet S8_Secuencia_Grua
A1: S8 — Secuencia por montaje y chequeo de grúa
A4: Secuencia de fabricación = secuencia del plan de montaje (E6); lotes en S9.
A6: Pieza crítica | B6: Peso (t) | C6: Costo de partir | D6: Nota
A7: Marco M-12 | B7: 14.2 | C7: 38000 | D7: Excede capacidad de grúa en radio de montaje
A8: Trabe TP-4 | B8: 12.8 | C8: 38000 | D8: Ídem
A9: Total partir piezas críticas | B9: =COUNT(B7:B8)&" piezas" -> 2 piezas | C9: =SUM(C7:C8) -> 76000

Sheet S9_Lotes
A1: S9 — Lotes con balance de capacidad (invariante 11)
A4: Concepto | B4: Sem 1 | C4: Sem 2 | D4: Sem 3 | E4: Sem 4 | F4: Sem 5
A5: HH requeridas por lote | B5: 880 | C5: 1520 | D5: 960 | E5: 840 | F5: 400
A6: HH libres de planta (E7) | B6: =Parametros_Version!$B$13 -> 600 | C6: =Parametros_Version!$B$13 -> 600 | D6: =Parametros_Version!$B$13 -> 600 | E6: =Parametros_Version!$B$13 -> 600 | F6: =Parametros_Version!$B$13 -> 600
A7: Déficit (HH) | B7: =MAX(0,B5-B6) -> 280 | C7: =MAX(0,C5-C6) -> 920 | D7: =MAX(0,D5-D6) -> 360 | E7: =MAX(0,E5-E6) -> 240 | F7: =MAX(0,F5-F6) -> 0
A8: Déficit Semana 2 | B8: =C7 -> 920
A9: Costo si se resuelve a fuerza (esc. A) | B9: =S9_Lotes!$B$8*Parametros_Version!$B$12 -> 145521

Sheet S10_Checklist_RSS
A1: S10 — Checklist e incertidumbre RSS (invariante 7)
A4: Componente de incertidumbre | B4: ±%
A5: Precio de material | B5: 0.0624
A6: Mano de obra / productividad | B6: 0.046
A7: Montaje y velocidad | B7: 0.036
A8: Desviaciones de concurso | B8: 0.026
A9: Financiero | B9: 0.02
A10: Otros | B10: 0.0145
A11: RSS (raíz de suma de cuadrados) | B11: =SQRT(SUMSQ(B5:B10)) -> 0.092693096
A12: Semáforo (fase) | B12: =IF(S10_Checklist_RSS!$B$11<0.05,"VERDE",IF(S10_Checklist_RSS!$B$11<0.1,"ÁMBAR","ROJO")) -> ÁMBAR
A14: Checklist de emisión (rúbrica, extracto)
A15: Peso único y doble chequeo — OK
A16: Exclusiones explícitas — OK
A17: Desviaciones con costo — OK
A18: Déficit explícito — OK
A19: Precios confirmados (Bitacora) — OK
A20: Leyenda de alcance — OK

Sheet S12_Programa
A1: S12 — Decisión de programa optimizada (invariante 14)
A2: Carga combinada en HH y t/sem con % de ocupación de habilitado; alerta ≥100%.
A4: t/sem | B4: Sem 1 | C4: Sem 2 | D4: Sem 3 | E4: Sem 4 | F4: Sem 5
A5: Proyectos en curso | B5: 40 | C5: 45 | D5: 38 | E5: 42 | F5: 45
A6: Proyecto nuevo | B6: 27 | C6: 38 | D6: 22 | E6: 28 | F6: 0
A7: Carga combinada (t/sem) | B7: =B5+B6 -> 67 | C7: =C5+C6 -> 83 | D7: =D5+D6 -> 60 | E7: =E5+E6 -> 70 | F7: =F5+F6 -> 45
A9: Habilitado (HH) | B9: Sem 1 | C9: Sem 2 | D9: Sem 3 | E9: Sem 4 | F9: Sem 5
A10: HH requeridas | B10: 534 | C10: 666 | D10: 480 | E10: 558 | F10: 360
A11: Capacidad (HH/sem) | B11: =Parametros_Version!$B$13 -> 600 | C11: =Parametros_Version!$B$13 -> 600 | D11: =Parametros_Version!$B$13 -> 600 | E11: =Parametros_Version!$B$13 -> 600 | F11: =Parametros_Version!$B$13 -> 600
A12: % ocupación de habilitado | B12: =B10/B11 -> 0.89 | C12: =C10/C11 -> 1.11 | D12: =D10/D11 -> 0.8 | E12: =E10/E11 -> 0.93 | F12: =F10/F11 -> 0.6
A13: Límite | B13: 1 | C13: 1 | D13: 1 | E13: 1 | F13: 1
A14: Alerta ≥100% | B14: =IF(B12>=1,"ALERTA","") | C14: =IF(C12>=1,"ALERTA","") -> ALERTA | D14: =IF(D12>=1,"ALERTA","") | E14: =IF(E12>=1,"ALERTA","") | F14: =IF(F12>=1,"ALERTA","")
A16: Optimización B* (minimizar tiempo y costo del retraso)
A17: Sobretiempo aplicado (HH) | B17: 1000
A18: HH a desplazar (excedente) | B18: 600
A19: Retraso mínimo (semanas) | B19: =CEILING(B18/Parametros_Version!$B$13,1) -> 1
A20: Costo del escenario B* | B20: 64148
A21: Pena máxima soportable | B21: 81373
A23: Escenario | B23: Costo | C23: Utilidad
A24: Utilidad sin costo de resolución | C24: 896603
A25: A — fuerza bruta | B25: =S9_Lotes!$B$9 -> 145521 | C25: =$C$24-B25 -> 751082
A26: B — mezcla estándar | B26: 115025 | C26: =$C$24-B26 -> 781578
A27: B* — optimizado | B27: =B20 -> 64148 | C27: =$C$24-B27 -> 832455
A28: C — no entrar | B28: 0 | C28: Nunca se recomienda bajo equilibrio
A29: RECOMENDACIÓN | B29: escenario_b_optimizado
A30: ADVERTENCIA OBLIGATORIA: comunicar y acordar el retraso de 1 semana con el cliente del proyecto afectado ANTES de comprometer el nuevo contrato (sin acuerdo → Escenario A). Registrar la reprogramación en E7.

Sheet LEAN
A1: LEAN — Métrica única de eficiencia (invariante 9)
A4: Costo base de transformación del caso | B4: 5110274
A5: Ahorro Lean verificable | B5: 0.084
A6: Ahorro Lean ($) | B6: =B4*B5 -> 429263.02
A7: Gainsharing | C7: La misma métrica (ahorro HH/ton) alimenta motor y gainsharing; el personal participa del ahorro VERIFICADO, no del estimado. Se audita en el cierre (inv. 16).

Sheet Rentabilidad
A1: Rentabilidad de planta
A4: Volumen contratado (t/mes) | B4: =S11_Velocidad!$B$10 -> 318
A5: Punto de equilibrio (t/mes) | B5: =S11_Velocidad!$B$11 -> 490
A6: Equilibrio con Lean (t/mes) | B6: =S11_Velocidad!$B$12 -> 368
A7: Estado | B7: =IF(B4<B5,"BAJO EQUILIBRIO — advertencia activa","OK") -> BAJO EQUILIBRIO — advertencia activa | C7: El escenario C (no entrar) nunca se recomienda con la planta bajo equilibrio (inv. 14).

Sheet Evidencia
A1: Evidencia
A4: Caso Lean 30% | B4: Caso documentado en proyecto específico; se comunica como evidencia, nunca como garantía (promesa conservadora 8–13%).
A5: Reconciliación de métodos | B5: APU vs Más 6% a margen comparable: 0.57% (<1%).
A6: Golden test | B6: Todos los valores de este libro reproducen el caso de referencia del documento rector v1.7.
A7: Bitácora de precios | B7: Confirmación registrada en Bitacora_Precios; ver invariante 8.

Sheet VE
A1: VE — Ingeniería de valor
A2: Propuestas NO incluidas en el precio; se ofrecen por separado.
A4: Propuesta | B4: Ahorro potencial | C4: Estado
A5: Optimizar familia de perfiles W (sustitución por sección eficiente) | B5: 118000 | C5: Propuesta — requiere aprobación del EOR/cliente
A6: Conexión alternativa en marcos secundarios | B6: 64000 | C6: Propuesta — requiere aprobación del EOR/cliente
A7: Recubrimiento por zonas de exposición | B7: 42000 | C7: Propuesta — requiere aprobación del EOR/cliente
A8: Total potencial | B8: =SUM(B5:B7) -> 224000

Sheet Bitacora_Precios
A1: Bitácora — confirmar_precios_mp (invariante 8, v1.7)
A2: Sin confirmación explícita registrada NO se emite precio de licitación. La confirmación queda ligada a la oferta.
A4: Material | B4: Precio $/kg | C4: Fuente | D4: Fecha | E4: Vigencia (d) | F4: Confirmado | G4: Por
A5: Perfil W (A992) | B5: =E3_Precios!$B$5 -> 24.8 | C5: =E3_Precios!$C$5 -> Cotización molino | D5: =E3_Precios!$D$5 -> 2026-07-21 | E5: =E3_Precios!$E$5 -> 9 | F5: SÍ | G5: Dirección
A6: Placa (A572-50) | B6: =E3_Precios!$B$6 -> 26.1 | C6: =E3_Precios!$C$6 -> Distribuidor | D6: =E3_Precios!$D$6 -> 2026-07-24 | E6: =E3_Precios!$E$6 -> 12 | F6: SÍ | G6: Dirección
A7: HSS (A500-C) | B7: =E3_Precios!$B$7 -> 28.35 | C7: =E3_Precios!$C$7 -> Distribuidor | D7: =E3_Precios!$D$7 -> 2026-07-18 | E7: =E3_Precios!$E$7 -> 6 | F7: SÍ | G7: Dirección
A8: Soldadura FCAW E71T-1 | B8: =E3_Precios!$B$8 -> 118 | C8: =E3_Precios!$C$8 -> Proveedor | D8: =E3_Precios!$D$8 -> 2026-07-15 | E8: =E3_Precios!$E$8 -> 30 | F8: SÍ | G8: Dirección
A9: Fecha de confirmación | B9: 2026-08-01
A10: Referencia de oferta | B10: OF-2026-014
A11: ESTADO DE EMISIÓN | B11: =IF(COUNTIF(F5:F8,"SÍ")=ROWS(F5:F8),"EMISIÓN HABILITADA","BLOQUEADA — CONFIRMAR PRECIOS") -> EMISIÓN HABILITADA

Sheet Interferencia_Familias
A1: alerta_interferencia_familias (invariante 3, v1.7)
A2: Se emite cuando una familia de HH altas satura habilitado y reduce la productividad de familias más rentables. Nunca se suprime.
A4: Estado en este proyecto | B4: NO_APLICA — una sola familia/clase (40 HH/t)
A6: Estructura de la alerta (EJEMPLO ilustrativo, no es este proyecto)
A7: Familias involucradas | B7: Misceláneos (90 HH/t) | C7: Armaduras (24 HH/t)
A8: Tonelaje | B8: 80 t | C8: 320 t
A9: HH en conflicto | B9: 210 HH/sem (Sem 3–5)
A10: Rentabilidad relativa | B10: $31/HH de margen | C10: $58/HH de margen
A11: Impacto estimado | B11: Armaduras −12% productividad → 380 HH extra
A12: Opciones (decide dirección) | B12: Repriorizar · partir lote · subcontratar misceláneos · aceptar impacto documentado
A14: La IA propone opciones con su costo; la dirección dispone. La alerta viaja con la oferta.

Sheet Cierre_Proyecto
A1: Cierre de proyecto — invariante 16 (v1.7)
A2: Llenar al concluir. Desviación > ±5% genera propuesta de recalibración; aprueba dirección; todo cambio = nueva versión de parámetros.
A4: Estado de este proyecto | B4: PENDIENTE DE CIERRE | E4: Sin cierre registrado, los datos NO alimentan recalibraciones.
A6: Celdas amarillas = llenar al cierre. La fila marcada EJEMPLO muestra el formato esperado.
A7: Rubro | B7: Presupuestado | C7: Real | D7: Desv. % | E7: Nota
A8: Costo total | B8: =S6_Financiero!$B$7 -> 6183408 | D8: =IF(C8="","",IF(B8=0,"",C8/B8-1))
A9: HH por familia (total) | B9: 4000 | D9: =IF(C9="","",IF(B9=0,"",C9/B9-1))
A10: HH/ton efectivas | B10: 40 | D10: =IF(C10="","",IF(B10=0,"",C10/B10-1))
A11: Desperdicio | B11: 0.0664 | D11: =IF(C11="","",IF(B11=0,"",C11/B11-1))
A12: Peso final de taller (t) | B12: 106 | D12: =IF(C12="","",IF(B12=0,"",C12/B12-1))
A13: Acero pagado ($/kg prom.) | B13: 25 | D13: =IF(C13="","",IF(B13=0,"",C13/B13-1))
A14: Costo de montaje | B14: 0 | D14: =IF(C14="","",IF(B14=0,"",C14/B14-1))
A15: Desviaciones de concurso ($) | B15: 188200 | D15: =IF(C15="","",IF(B15=0,"",C15/B15-1))
A16: EJEMPLO — HH/ton efectivas (otro proyecto) | B16: 40 | C16: 43.1 | D16: =C16/B16-1 -> 0.0775 | E16: Desv. +7.8% > 5% → generó propuesta: clase 40 → 43 HH/t (evidencia: 3 proyectos). Aprobación: dirección. Nueva versión: v2026.2.
A18: Propuesta de recalibración | B18: =IF(COUNT(C8:C15)=0,"—","REVISAR DESVIACIONES > 5%") -> — | E18: Los parámetros NUNCA se recalibran solos (versionado en Parametros_Version).
