Workbook
Name OUT_ALERTAS_AREA: '14_INTERFAZ_MOTOR'!$C$29
Name OUT_AREA_M2: '14_INTERFAZ_MOTOR'!$C$17
Name OUT_COSTO_ABRASIVO: '14_INTERFAZ_MOTOR'!$C$25
Name OUT_COSTO_APLICACION: '14_INTERFAZ_MOTOR'!$C$26
Name OUT_COSTO_KG: '14_INTERFAZ_MOTOR'!$C$28
Name OUT_COSTO_M2: '14_INTERFAZ_MOTOR'!$C$27
Name OUT_COSTO_PINTURA: '14_INTERFAZ_MOTOR'!$C$23
Name OUT_CUNETES: '14_INTERFAZ_MOTOR'!$C$22
Name OUT_KG_ABRASIVO: '14_INTERFAZ_MOTOR'!$C$24
Name OUT_LITROS_DESPERDICIO: '14_INTERFAZ_MOTOR'!$C$21
Name OUT_LITROS_PRACTICOS: '14_INTERFAZ_MOTOR'!$C$20
Name OUT_LITROS_TEORICOS: '14_INTERFAZ_MOTOR'!$C$19
Name OUT_PESO_KG: '14_INTERFAZ_MOTOR'!$C$18
Name OUT_PU_CELOSIA: '14_INTERFAZ_MOTOR'!$C$35
Name OUT_PU_COLUMNA: '14_INTERFAZ_MOTOR'!$C$33
Name OUT_PU_CONTRAVENTEO: '14_INTERFAZ_MOTOR'!$C$36
Name OUT_PU_MISCELANEO: '14_INTERFAZ_MOTOR'!$C$37
Name OUT_PU_PLACA: '14_INTERFAZ_MOTOR'!$C$38
Name OUT_PU_VIGA: '14_INTERFAZ_MOTOR'!$C$34

Sheet 0_PASO_A_PASO
B2: INSTRUCTIVO PASO A PASO — ESTIMACIÓN DE APLICACIÓN DE PINTURA
B3: Siga los pasos en orden. Tiempo estimado la primera vez: 2–3 horas con el modelo en mano; 30–45 min en proyectos siguientes (los factores ya quedan calibrados). Regla general del archivo: solo se capturan celdas AZULES; las negras y verdes se calculan solas. Celdas con fondo AMARILLO = supuestos que exigen calibración antes de usar en una oferta.
B5: FASE 0 — ANTES DE ABRIR EL ARCHIVO: REÚNA LA INFORMACIÓN
B6: 0.1 | C6: Documentos del proyecto | D6: Tenga a la mano: (a) la especificación de pintura del proyecto (sistema de capas, EPS por capa, grado de limpieza SP y perfil de anclaje requerido, categoría de corrosividad C1–C5 y, si aplica, el rating ignífugo R30/R60/R90/R120); (b) las hojas técnicas (TDS) de cada producto del sistema propuesto; (c) el reporte de piezas del modelo Tekla/IFC con áreas y pesos, o —si aún no hay modelo— el tonelaje estimado por familia; (d) cotizaciones vigentes de pintura (por cuñete) y abrasivo (por saco o súper saco).
B7: 0.2 | C7: Verifique compatibilidad del sistema | D7: Confirme en los TDS que las capas son compatibles entre sí (el fabricante lo indica) y que el primario está aprobado para el perfil de anclaje especificado. Si hay intumescente, pida al fabricante la CARTA DE ESPESORES CERTIFICADA (por Hp/A y rating) — sin ella no se puede presupuestar en serio. Este es un punto de decisión suya, no del archivo.
B8: 0.3 | C8: Defina el alcance de aplicación | D8: Aclare con el cliente qué se pinta en taller y qué en obra, si el retoque de montaje está en su alcance, y qué superficies quedan explícitamente SIN pintura (slip-critical, embebidos, zonas de soldadura de campo). Esto cambia áreas, ambientes de aplicación y responsabilidades.
B9: FASE 1 — CAPTURE LOS PRODUCTOS (HOJA 2_HOJA_TECNICA)
B10: 1.1 | C10: Un renglón por producto | D10: Capture cada producto del sistema (primario, intermedio, acabado, intumescente, sellador si aplica) en un renglón: nombre comercial, fabricante, tipo genérico, % sólidos por volumen (del TDS, "sin diluir"), EPS mínimo/recomendado/máximo, litros por cuñete, si es intumescente (SI/NO) y precio por cuñete de la cotización vigente.
B11: 1.2 | C11: Cuidado con el % de sólidos | D11: El TDS a veces da dos valores: sólidos por VOLUMEN y sólidos por PESO. El que usa este modelo es POR VOLUMEN. Si el TDS solo da por peso, pida el dato al proveedor. Capturarlo mal distorsiona todo el rendimiento.
B12: 1.3 | C12: Verifique el rendimiento calculado | D12: La columna "Rend. teórico" debe parecerse al rendimiento teórico que declara el propio TDS al mismo espesor. Si difiere más de ±5%, hay un error de captura (espesor en mils en lugar de micras es el clásico).
B13: FASE 2 — CALIBRE LOS FACTORES DE DESPERDICIO (HOJA 3_FACTORES)
B14: 2.1 | C14: Primera vez: revise, no acepte | D14: Las tablas A (forma), B (ambiente/método), C (perfil de anclaje) y D (entre capas, equipo, intumescente, franjeo) traen valores típicos de la industria. NO son de METALITEC: son el punto de partida. Léalas con su supervisor de pintura y ajuste lo que su experiencia contradiga.
B15: 2.2 | C15: Calibración con datos reales | D15: La calibración seria se hace así: tome 3–5 órdenes de trabajo cerradas, con litros realmente consumidos (vales de almacén) y m² realmente pintados por tipo de pieza. Calcule el consumo real por m², compárelo contra el teórico del TDS y despeje el % de pérdida real. Ajuste las tablas hasta que el modelo reproduzca esos consumos históricos con ±5% de error. Documente la fecha de calibración en un comentario de celda.
B16: 2.3 | C16: Perfil de anclaje | D16: En la Tabla C verifique que el rango de perfil corresponda a lo que su granalladora realmente produce (mídalo con cinta réplica Testex en 2–3 piezas). Si su mezcla operativa da 65 µm y el proyecto pide 50–75, use R2/R3 según el caso.
B17: FASE 3 — DETERMINE EL ÁREA A PINTAR (HOJAS 12_ESTIMACION Y 10_PIEZAS)
B18: 3.1 | C18: ¿Tiene modelo o solo tonelaje? | D18: CAMINO A (sin modelo, cotización temprana): vaya a 12_ESTIMACION, capture el espesor promedio por familia (mm) y el % de área no pintable; con el tonelaje obtiene los m² estimados pintables. Use esos m² para las fases 4–6. CAMINO B (con modelo Tekla/IFC): llene 10_PIEZAS con el reporte de piezas — marca, familia, cantidad, área y peso unitarios — y use las áreas reales. Puede subir el archivo de exportación a Claude para que llene la tabla.
B19: 3.2 | C19: Pida el reporte correcto | D19: Al área del modelo pídale SOLO área pintable: sin interior de HSS, sin caras de contacto con concreto, sin superficies slip-critical. Si el reporte trae área total (lo usual en Tekla), descuéntelo con el % no pintable de 12_ESTIMACION, columna F.
B20: 3.3 | C20: Valide con el semáforo | D20: Con ambos caminos disponibles, 12_ESTIMACION compara estimado vs. real por familia. Si una familia marca ⚠ REEVALUAR (diferencia > tolerancia, default ±15%), NO avance: revise en este orden (a) el espesor promedio supuesto contra los perfiles reales de esa familia, (b) si el reporte del modelo incluye superficies no pintables, (c) piezas duplicadas o faltantes en 10_PIEZAS. Avanzar con áreas malas invalida todo lo que sigue.
B21: FASE 4 — CALCULE CONSUMO Y DESPERDICIO DE PINTURA (HOJA 4_CALCULO)
B22: 4.1 | C22: Arme las partidas | D22: Agrupe las piezas en partidas que compartan: misma forma dominante (F1–F7), mismo ambiente/método (A1–A6), mismo perfil de anclaje (R0–R4) y mismo sistema de capas. Típicamente coinciden con las familias de 10_PIEZAS, pero puede subdividir (p. ej., "vigas con ignífugo" aparte de "vigas normales").
B23: 4.2 | C23: Una fila por capa | D23: Cada partida ocupa tantas filas como capas tenga el sistema: capa 1 = primario, capa 2 = intermedio, capa 3 = acabado (y las que apliquen: intumescente, sellador). Repita en cada fila el área y los códigos de la partida; cambie solo el N° de capa, el ID de producto y el EPS especificado de esa capa.
B24: 4.3 | C24: Franjeo en la capa correcta | D24: Marque "SI" en franjeo normalmente en la capa 1 (o donde la especificación pida el stripe coat). No lo marque en todas las capas: duplicaría el recargo.
B25: 4.4 | C25: Lea los resultados | D25: Por cada capa el modelo entrega: EPS corregido (la capa 1 sube por el volumen muerto del perfil de anclaje), rendimiento teórico, litros teóricos, % de pérdida total compuesta, litros prácticos y LITROS DE DESPERDICIO explícitos. Verifique que los % de pérdida le hagan sentido: placa en taller ~15–20%, viga W ~25%, celosía ~45–50%, intumescente +12 puntos adicionales. Si algo sale fuera de esos órdenes, revise los códigos capturados.
B26: FASE 5 — ABRASIVO (HOJA 7_ABRASIVO)
B27: 5.1 | C27: Elija el sistema de blasteo | D27: Por partida: AB2 si la pieza pasa por la máquina de granallado (lo normal en perfiles), AB3 si va a cuarto manual (piezas fuera de gálibo, retrabajos), AB1 solo si se blastea con arena/escoria a cielo abierto (campo). El grado (SP6/SP10/SP5) viene de la especificación del proyecto.
B28: 5.2 | C28: Capture precios y presentaciones | D28: En la Tabla E ponga el precio vigente por presentación (saco 25 kg de granalla, súper saco de arena) y ajuste la presentación a la de su proveedor. El modelo redondea la compra a presentaciones completas.
B29: 5.3 | C29: Calibre la atrición | D29: El consumo de granalla precargado (kg/m²) es genérico. Su dato real: kg de granalla repuestos en el periodo ÷ m² procesados en el mismo periodo (vales de almacén vs. reporte de producción). Es el número que más varía entre plantas.
B30: FASE 6 — COMPRA Y APU (HOJAS 5_RESUMEN Y 11_APU)
B31: 6.1 | C31: Revise la compra en cuñetes | D31: 5_RESUMEN consolida litros prácticos por producto, redondea a cuñetes completos (ROUNDUP) y muestra el colchón de redondeo y el costo. Verifique: (a) que ningún producto quede con consumo cero inesperado, (b) que el colchón de redondeo sea razonable — si un producto compra 1 cuñete para usar 2 litros, evalúe presentación menor o compartir con otra OT.
B32: 6.2 | C32: Arme el APU por familia | D32: En 11_APU: copie las referencias verdes de material ($/m² pintura y abrasivo del proyecto) como punto de partida en las columnas azules, ajuste por familia si los sistemas difieren, capture HH/m² por familia (calibre con OTs reales — misma disciplina que su HH/ton), tarifa $/HH, equipo $/m² y el % de indirectos + utilidad según la política comercial vigente.
B33: 6.3 | C33: Elija la unidad de venta | D33: Seleccione m2 o kg por familia según cómo cotiza el cliente. Verifique el PU en kg contra su intuición: la celosía SIEMPRE debe salir varias veces más cara por kg que la placa. Si no, hay un error de áreas o de ratio kg/m².
B34: 6.4 | C34: Costo por pieza | D34: 10_PIEZAS ya muestra el costo de pintura por pieza, en $/m² y $/kg, tomando el PU de su familia. Útil para valuar avances, cambios de alcance y reclamos.
B35: FASE 7 — VALIDACIÓN FINAL ANTES DE OFERTAR (ZONA COPILOTO: SU FIRMA)
B36: 7.1 | C36: Checklist de cierre | D36: Antes de pasar los números a la oferta verifique: □ ninguna familia en ⚠ REEVALUAR en 12_ESTIMACION; □ factores de 3_FACTORES calibrados o al menos revisados con el supervisor; □ TDS reales capturados (no los ejemplos P01–P04); □ precios de pintura y abrasivo con cotización vigente (no en cero); □ si hay intumescente, EPS tomado de la carta certificada por Hp/A, no de la tabla ilustrativa; □ % indirectos + utilidad autorizado por dirección.
B37: 7.2 | C37: Prueba de sensibilidad | D37: Cambie ±10% el factor de forma dominante y el precio del producto más caro, y observe cuánto se mueve el costo total. Si la oferta es sensible (>5% del total), documente el supuesto en la oferta como condición (p. ej., "considera aplicación en taller; aplicación en campo se cotiza aparte").
B38: 7.3 | C38: Cierre del ciclo (mejora continua) | D38: Al terminar el proyecto, compare litros comprados vs. consumidos vs. lo que este modelo predijo, por producto y por partida. La diferencia alimenta la recalibración de 3_FACTORES y 7_ABRASIVO (paso 2.2). Con 3–4 proyectos cerrados, el modelo queda ajustado a SU planta y las ofertas se vuelven defendibles con datos, no con criterio.
B39: 7.4 | C39: Errores comunes a evitar | D39: (1) Capturar EPS en mils creyendo que son micras (todo el consumo sale 25 veces mal). (2) Usar el área total del modelo sin descontar no pintables. (3) Olvidar el sellador del intumescente como capa. (4) Marcar franjeo en todas las capas. (5) Presupuestar intumescente con un EPS promedio en lugar de por Hp/A. (6) Dejar precios en cero y ofertar solo con litros. (7) No respetar la ventana máxima de repintado en la programación: el lijado no está en este modelo y come el margen.
B41: Recuerde el marco de trabajo: este archivo PROPONE (Zona Copiloto). Los factores calibrados, los precios, la unidad de venta y la oferta final los valida y firma la dirección. Ningún número sale de aquí a un cliente sin pasar por los pasos 7.1 a 7.3.
B43: ACTUALIZACIÓN: use la hoja 13_PANEL como tablero de captura y resultados (uso directo en Excel), la hoja 14_INTERFAZ_MOTOR para la integración con el Motor IFC/presupuesto, y el asistente de 6_IGNIFUGO para repartir el intumescente entre planta y sitio (dos filas en 4_CALCULO: planta=A1, sitio=A4/A6).
B44: ACTUALIZACIÓN 2: antes de calcular el abrasivo, determine la condición inicial del acero (grados A/B/C/D de ISO 8501-1, Tabla F de 7_ABRASIVO) inspeccionando el material en patio: acero nuevo con calamina o acero viejo picado consumen 30–90% más abrasivo que la condición base, y el acero picado altera el perfil de anclaje real (medir con Testex y ajustar la Tabla C).

Sheet 13_PANEL
B2: PANEL DE CONTROL — CAPTURA GUIADA Y RESULTADOS
B3: Una sola vista para usar el archivo sin perderse: la columna ESTADO le dice qué falta por capturar (se pone OK sola cuando termina cada paso) y abajo están los resultados del presupuesto en vivo. El detalle vive en las demás hojas; aquí solo se supervisa.
B5: CHECKLIST DE CAPTURA (en orden)
B6: Paso | C6: Estado | E6: Dónde y qué capturar
B7: 1. Productos de pintura (TDS) capturados | C7: =IF(COUNT('2_HOJA_TECNICA'!F6:F13)>=1,"OK","FALTA") -> OK | E7: Hoja 2_HOJA_TECNICA: un renglón por producto con % sólidos por volumen, espesores y litros por cuñete, copiados de la hoja técnica.
B8: 2. Precios de pintura capturados | C8: =IF(SUMPRODUCT(--('2_HOJA_TECNICA'!L6:L13>0))>=1,"OK","FALTA") -> FALTA | E8: Hoja 2_HOJA_TECNICA columna L: precio por cuñete de la cotización vigente. Sin precio, el costo sale en cero.
B9: 3. Factores de desperdicio revisados | C9: =IF($C$16="SI","OK","PENDIENTE") -> PENDIENTE | E9: Hoja 3_FACTORES: revise las 4 tablas con su supervisor de pintura y ajuste las celdas amarillas. Cuando lo haga, ponga SI en la celda azul de la derecha →
B10: 4. Piezas o áreas capturadas | C10: =IF(COUNTA('10_PIEZAS'!B6:B35)>=1,"OK","FALTA") -> OK | E10: Hoja 10_PIEZAS (si hay modelo Tekla/IFC) o hoja 12_ESTIMACION (si solo hay tonelaje: espesor promedio + % no pintable por familia).
B11: 5. Áreas validadas (sin alertas) | C11: =IF(COUNTIF('12_ESTIMACION'!K8:K13,"⚠ REEVALUAR")=0,"OK",COUNTIF('12_ESTIMACION'!K8:K13,"⚠ REEVALUAR")&" FAMILIAS EN ALERTA") -> 5 FAMILIAS EN ALERTA | E11: Hoja 12_ESTIMACION: ninguna familia debe quedar en ⚠ REEVALUAR. Si hay alertas, corrija espesor promedio, % no pintable o el listado de piezas antes de seguir.
B12: 6. Partidas y capas capturadas | C12: =IF(COUNTA('4_CALCULO'!B6:B25)>=1,"OK","FALTA") -> OK | E12: Hoja 4_CALCULO: una fila por capa de cada partida. Si hay intumescente, capture DOS filas (planta y sitio) usando el asistente de 6_IGNIFUGO.
B13: 7. Abrasivo capturado con precio | C13: =IF(AND(COUNTA('7_ABRASIVO'!B14:B28)>=1,SUMPRODUCT(--('7_ABRASIVO'!J7:J9>0))>=1),"OK","FALTA") -> FALTA | E13: Hoja 7_ABRASIVO: partidas de blasteo + precio por presentación de arena/granalla en la Tabla E.
B14: 8. APU armado (MO, equipo, indirectos) | C14: =IF(SUMPRODUCT(--('11_APU'!G7:G12>0))>=1,"OK","PENDIENTE") -> PENDIENTE | E14: Hoja 11_APU: copie las referencias verdes de material a las columnas azules, capture HH/m², tarifa, equipo e indirectos, y elija la unidad m2/kg por familia.
B16: Confirmación factores revisados (escriba SI): | C16: NO
B18: RESULTADOS DEL PRESUPUESTO (en vivo)
B19: Indicador | C19: Valor
B20: Área pintable total (m²) | C20: ='10_PIEZAS'!H36 -> 1348.8
B21: Peso total (kg) | C21: ='10_PIEZAS'!I36 -> 69782
B22: Pintura — litros teóricos | C22: ='4_CALCULO'!N26 -> 1782.418
B23: Pintura — litros prácticos (con desperdicio) | C23: ='4_CALCULO'!P26 -> 2704.9836
B24: Pintura — litros de desperdicio | C24: ='4_CALCULO'!Q26 -> 922.56554
B25: Pintura — % desperdicio global | C25: =IF('4_CALCULO'!P26=0,"",'4_CALCULO'!Q26/'4_CALCULO'!P26) -> 0.34106142
B26: Pintura — cuñetes a comprar (total) | C26: ='5_RESUMEN'!I14 -> 127
B27: Pintura — costo de compra ($) | C27: ='5_RESUMEN'!L14 -> 0
B28: Abrasivo — kg a comprar | C28: ='7_ABRASIVO'!M29 -> 3650
B29: Abrasivo — costo de compra ($) | C29: ='7_ABRASIVO'!N29 -> 0
B30: Aplicación — costo total según APU ($) | C30: ='10_PIEZAS'!K36 -> 29671.312
B31: Aplicación — costo promedio $/m² | C31: =IF('10_PIEZAS'!H36=0,"",'10_PIEZAS'!K36/'10_PIEZAS'!H36) -> 21.998304
B32: Aplicación — costo promedio $/kg | C32: ='10_PIEZAS'!L36 -> 0.42520009
B34: Si todos los pasos del checklist están en OK y las cifras de arriba le hacen sentido, pase al checklist de cierre 7.1 del instructivo (hoja 0_PASO_A_PASO) antes de llevar estos números a la oferta.

Sheet 1_INSTRUCCIONES
B2: MOTOR DE PRESUPUESTO — MÓDULO PINTURA: DESPERDICIOS Y COMPRA EN CUÑETES
B3: METALITEC / Grupo Baysa — Sistemas de pintura sobre acero estructural (SSPC / ISO 12944)
B5: OBJETIVO | C5: Determinar la cantidad de pintura a comprar (en cuñetes) por cada producto del sistema, partiendo de la hoja técnica del fabricante, el perfil de anclaje especificado y el área a pintar, incorporando de forma explícita y auditable los factores de desperdicio: forma de la pieza, ambiente de aplicación, método de aplicación, corrección por perfil de anclaje y pérdidas entre capas. Incluye consideraciones para pinturas ignífugas (intumescentes).
B6: FLUJO DE USO | C6: 1) Capture cada producto de pintura en la hoja 2_HOJA_TECNICA transcribiendo los datos de la hoja técnica (TDS) del fabricante: % sólidos por volumen, EPS recomendado, presentación del cuñete, si es intumescente, etc. 2) Revise/calibre los factores de las tablas en 3_FACTORES (celdas azules = editables). 3) En 4_CALCULO capture cada partida: área, forma, ambiente, método, perfil de anclaje y el sistema de capas (producto + EPS por capa). 4) Lea el resultado: litros teóricos, % desperdicio total, litros prácticos y cuñetes a comprar. 5) 5_RESUMEN consolida la compra por producto. 6) Si hay intumescente, revise 6_IGNIFUGO para masividad Hp/A y sus reglas.
B7: CONVENCIÓN DE COLORES | C7: AZUL = dato de entrada (usted lo captura o calibra). NEGRO = fórmula (no tocar). VERDE = vínculo entre hojas. Fondo AMARILLO = supuesto clave que requiere calibración con datos reales de planta antes de usar en oferta.
B8: FÓRMULA BASE (SSPC) | C8: Rendimiento teórico (m²/L) = (% Sólidos por Volumen × 10) / EPS seco (µm). Consumo teórico (L) = Área (m²) / Rendimiento teórico. Consumo práctico (L) = Consumo teórico / (1 − % pérdida total). La pérdida total se compone multiplicativamente: (1−pérdida) = (1−p.forma) × (1−p.ambiente/método) × (1−p.entre capas), y la capa 1 lleva además la corrección de volumen muerto por perfil de anclaje.
B9: PERFIL DE ANCLAJE | C9: La rugosidad del granallado (p. ej. SSPC-SP10 con perfil 50–75 µm) consume pintura: los picos del perfil "roban" espesor a la primera capa (volumen muerto). Regla práctica de la industria (Hempel, Jotun, NACE): sumar al EPS de la capa 1 una corrección ≈ 1/3 a 2/3 del perfil de anclaje según rugosidad. La tabla en 3_FACTORES define la corrección por rango de perfil; solo aplica a la CAPA 1 (primario).
B10: DESPERDICIO REPORTADO | C10: El modelo reporta, por cada capa y por cada producto, el % de desperdicio total considerado y los litros de desperdicio (diferencia entre consumo práctico y teórico), para que Comercial pueda defender el APU y Compras conozca el excedente implícito.
B11: IGNÍFUGAS | C11: Si el producto está marcado como intumescente en 2_HOJA_TECNICA, el cálculo aplica automáticamente el recargo adicional de desperdicio de la tabla de 3_FACTORES (múltiples pasadas, alto espesor, malla en algunos casos) y la hoja 6_IGNIFUGO da la guía de EPS por masividad Hp/A. El EPS de intumescente NO sale del TDS genérico: sale del certificado del fabricante según Hp/A y tiempo de resistencia al fuego requerido (30/60/90/120 min). Zona Humana: la validación del espesor certificado es indelegable.
B12: ZONA COPILOTO | C12: La IA propone los factores típicos de la industria precargados; Daniel valida y calibra con mediciones reales de planta (consumo real vs. teórico por OT) y firma los volúmenes de compra. Los valores precargados NO deben usarse en una oferta sin calibración.

Sheet 2_HOJA_TECNICA
B2: CATÁLOGO DE PRODUCTOS — DATOS DE HOJA TÉCNICA (TDS) DEL FABRICANTE
B3: Capture en AZUL los datos tal como aparecen en la hoja técnica. Las columnas en negro se calculan solas.
B5: ID | C5: Producto / Nombre comercial | D5: Fabricante | E5: Tipo genérico | F5: % Sólidos x Volumen | G5: EPS mín (µm) | H5: EPS recom (µm) | I5: EPS máx (µm) | J5: Cuñete (L) | K5: ¿Intumescente? (SI/NO) | L5: Precio x cuñete ($) | M5: Rend. teórico @EPS recom (m²/L) | N5: Rend. teórico (m²/cuñete) | O5: Notas TDS (diluyente, pot-life, repintado)
B6: P01 | C6: Primario epóxico rico en zinc | D6: (capturar) | E6: Zinc epóxico | F6: 0.62 | G6: 50 | H6: 75 | I6: 100 | J6: 18.9 | K6: NO | L6: 0 | M6: =IF(OR(F6="",H6=""),"",F6*1000/H6) -> 8.2666667 | N6: =IF(M6="","",M6*J6) -> 156.24
B7: P02 | C7: Epóxico poliamida alto sólidos | D7: (capturar) | E7: Epóxico intermedio | F7: 0.8 | G7: 100 | H7: 125 | I7: 200 | J7: 18.9 | K7: NO | L7: 0 | M7: =IF(OR(F7="",H7=""),"",F7*1000/H7) -> 6.4 | N7: =IF(M7="","",M7*J7) -> 120.96
B8: P03 | C8: Acabado poliuretano alifático | D8: (capturar) | E8: Poliuretano acabado | F8: 0.6 | G8: 50 | H8: 75 | I8: 100 | J8: 18.9 | K8: NO | L8: 0 | M8: =IF(OR(F8="",H8=""),"",F8*1000/H8) -> 8 | N8: =IF(M8="","",M8*J8) -> 151.2
B9: P04 | C9: Intumescente base agua | D9: (capturar) | E9: Intumescente celulósico | F9: 0.69 | G9: 300 | H9: 1000 | I9: 3000 | J9: 25 | K9: SI | L9: 0 | M9: =IF(OR(F9="",H9=""),"",F9*1000/H9) -> 0.69 | N9: =IF(M9="","",M9*J9) -> 17.25
B10: P05 | K10: NO | L10: 0 | M10: =IF(OR(F10="",H10=""),"",F10*1000/H10) | N10: =IF(M10="","",M10*J10)
B11: P06 | K11: NO | L11: 0 | M11: =IF(OR(F11="",H11=""),"",F11*1000/H11) | N11: =IF(M11="","",M11*J11)
B12: P07 | K12: NO | L12: 0 | M12: =IF(OR(F12="",H12=""),"",F12*1000/H12) | N12: =IF(M12="","",M12*J12)
B13: P08 | K13: NO | L13: 0 | M13: =IF(OR(F13="",H13=""),"",F13*1000/H13) | N13: =IF(M13="","",M13*J13)
B14: Nota: Rend. teórico (m²/L) = %SV × 10 / EPS(µm) × 100 = %SV × 1000 / EPS. Ejemplo: 62% SV @ 75 µm → 8.27 m²/L. Los productos P01–P04 son EJEMPLOS genéricos: sustituya con el TDS real del proyecto.

Sheet 3_FACTORES
B2: TABLAS DE FACTORES DE DESPERDICIO (CALIBRAR CON DATOS DE PLANTA)
B4: TABLA A — FACTOR DE FORMA DE LA PIEZA (pérdida por overspray según geometría)
B5: Código | C5: Descripción de la pieza | D5: % Pérdida forma | G5: Criterio
B6: F1 | C6: Placa / superficie plana continua (tanques, placas) | D6: 0.05 | G6: Superficie continua, overspray mínimo; el abanico casi todo deposita.
B7: F2 | C7: Perfil pesado W/HP alma ancha (>200 mm de patín) | D7: 0.1 | G7: Caras anchas pero con cantos y filetes; algo de rebote en esquinas interiores.
B8: F3 | C8: Perfil mediano W/C/L (100–200 mm) | D8: 0.15 | G8: Relación perímetro/área alta; el abanico excede el ancho de la cara.
B9: F4 | C9: Perfil ligero / ángulos / redondos (<100 mm) | D9: 0.25 | G9: Gran parte del abanico pasa de largo; piezas angostas.
B10: F5 | C10: Celosía / armadura / joist (estructura abierta) | D10: 0.4 | G10: Estructura abierta: el aire pasa a través; pérdida típica 35–50%.
B11: F6 | C11: HSS / tubulares (solo exterior) | D11: 0.12 | G11: Superficie curva continua, pero el abanico envuelve y escapa tangencialmente.
B12: F7 | C12: Miscelánea compleja (conexiones, escaleras, barandal) | D12: 0.3 | G12: Geometría irregular, muchas caras pequeñas, retoque con brocha.
B15: TABLA B — AMBIENTE Y MÉTODO DE APLICACIÓN (pérdida por condiciones + eficiencia de transferencia)
B16: Código | C16: Ambiente / Método | D16: % Pérdida amb+mét | G16: Criterio
B17: A1 | C17: Taller controlado — Airless | D17: 0.1 | G17: Cabina/nave cerrada, sin viento; airless con eficiencia de transferencia 70–80%.
B18: A2 | C18: Taller controlado — Convencional (aire) | D18: 0.25 | G18: Pistola convencional: eficiencia 45–60% aun en ambiente controlado.
B19: A3 | C19: Taller controlado — Brocha/Rodillo | D19: 0.05 | G19: Casi sin overspray; pérdida por residuo en charola/rodillo y retoques.
B20: A4 | C20: Exterior / campo — Airless | D20: 0.2 | G20: Viento y condiciones variables: overspray se duplica vs. taller; incluye deriva.
B21: A5 | C21: Exterior / campo — Convencional (aire) | D21: 0.35 | G21: La peor combinación: baja transferencia + viento. Evitar si es posible.
B22: A6 | C22: Exterior / campo — Brocha/Rodillo (retoque montaje) | D22: 0.08 | G22: Retoques en obra: pérdida baja de aplicación pero botes abiertos y sobrantes.
B25: TABLA C — CORRECCIÓN POR PERFIL DE ANCLAJE (volumen muerto — SOLO CAPA 1 / PRIMARIO)
B26: Código | C26: Perfil de anclaje especificado | D26: Perfil (µm) | E26: µm extra a sumar al EPS capa 1 | G26: Criterio
B27: R0 | C27: Sin granallado / SP2-SP3 (limpieza manual) | D27: 0 | E27: 0 | G27: Sin perfil generado: no hay volumen muerto significativo.
B28: R1 | C28: Perfil fino 25–40 µm (SP6 ligero) | D28: 40 | E28: 15 | G28: ≈1/3 del perfil: rugosidad fina, poco volumen muerto.
B29: R2 | C29: Perfil medio 40–60 µm (SP6 / SP10 típico) | D29: 60 | E29: 25 | G29: ≈40–50% del perfil. Rango más común en estructura.
B30: R3 | C30: Perfil grueso 60–85 µm (SP10 / SP5 con abrasivo angular) | D30: 85 | E30: 40 | G30: ≈50% del perfil: picos altos consumen primario.
B31: R4 | C31: Perfil muy grueso >85 µm (granalla angular gruesa / intumescente) | D31: 100 | E31: 60 | G31: ≈60% del perfil; usual para intumescentes y zinc silicato.
B34: TABLA D — PÉRDIDAS ENTRE CAPAS Y RECARGOS ADICIONALES
B35: Código | C35: Concepto | D35: % Pérdida | G35: Criterio
B36: D1 | C36: Pérdida entre capas (capa 2 en adelante) | D36: 0.05 | G36: Retoques de puntos bajos detectados con medidor, lijado/reactivación, franjeo (stripe coat) no medido aparte.
B37: D2 | C37: Residuo en envase, mangueras y equipo (por producto/lote) | D37: 0.04 | G37: Pintura que queda en cuñete, bomba, mangueras, filtros y purgas al cambiar de color/producto.
B38: D3 | C38: Recargo pintura INTUMESCENTE (adicional) | D38: 0.12 | G38: Altos espesores en múltiples pasadas, descuelgues, control de EPS húmedo pasada por pasada, mermas por pot-life en base solvente.
B39: D4 | C39: Recargo franjeo / stripe coat en cantos y soldaduras (si no se cuantifica su área) | D39: 0.03 | G39: Cordón adicional a brocha en cantos, tornillos y soldaduras; consume producto no capturado en el área plana.
B41: Composición: (1−Pérdida total) = (1−forma) × (1−amb/mét) × (1−entre capas si aplica) × (1−residuo equipo) × (1−intumescente si aplica) × (1−franjeo si aplica). La corrección por perfil de anclaje NO es un %: se suma en µm al EPS de la capa 1.

Sheet 4_CALCULO
B2: CÁLCULO DE CONSUMO Y DESPERDICIO POR PARTIDA Y CAPA
B3: Una fila por CAPA de cada partida. Capture las celdas azules; use los códigos de 3_FACTORES y los ID de producto de 2_HOJA_TECNICA.
B5: Partida | C5: Descripción | D5: Área (m²) | E5: Forma (F1-F7) | F5: Amb/Mét (A1-A6) | G5: Perfil ancl. (R0-R4) | H5: N° capa (1,2,3…) | I5: ID Prod. | J5: EPS espec. capa (µm) | K5: ¿Franjeo? (SI/NO) | L5: EPS corregido (µm) | M5: Rend. teórico (m²/L) | N5: Litros teóricos | O5: % Pérdida total | P5: Litros prácticos | Q5: Litros desperdicio | R5: Cuñete (L) | S5: Cuñetes (info capa)
B6: PT-01 | C6: Vigas principales W24 nave | D6: 1250 | E6: F2 | F6: A1 | G6: R2 | H6: 1 | I6: P01 | J6: 75 | K6: SI | L6: =IF($B6="","",J6+IF(H6=1,VLOOKUP(G6,'3_FACTORES'!$B$27:$E$31,4,0),0)) -> 100 | M6: =IF($B6="","",VLOOKUP(I6,'2_HOJA_TECNICA'!$B$6:$K$13,5,0)*1000/L6) -> 6.2 | N6: =IF($B6="","",D6/M6) -> 201.6129 | O6: =IF($B6="","",1-(1-VLOOKUP(E6,'3_FACTORES'!$B$6:$D$12,3,0))*(1-VLOOKUP(F6,'3_FACTORES'!$B$17:$D$22,3,0))*(1-IF(H6>1,'3_FACTORES'!$D$36,0))*(1-'3_FACTORES'!$D$37)*(1-IF(VLOOKUP(I6,'2_HOJA_TECNICA'!$B$6:$K$13,10,0)="SI",'3_FACTORES'!$D$38,0))*(1-IF(K6="SI",'3_FACTORES'!$D$39,0))) -> 0.245728 | P6: =IF($B6="","",N6/(1-O6)) -> 267.29469 | Q6: =IF($B6="","",P6-N6) -> 65.68179 | R6: =IF($B6="","",VLOOKUP(I6,'2_HOJA_TECNICA'!$B$6:$K$13,9,0)) -> 18.9 | S6: =IF($B6="","",P6/R6) -> 14.142576
B7: PT-01 | C7: Vigas principales W24 nave | D7: 1250 | E7: F2 | F7: A1 | G7: R2 | H7: 2 | I7: P02 | J7: 125 | K7: NO | L7: =IF($B7="","",J7+IF(H7=1,VLOOKUP(G7,'3_FACTORES'!$B$27:$E$31,4,0),0)) -> 125 | M7: =IF($B7="","",VLOOKUP(I7,'2_HOJA_TECNICA'!$B$6:$K$13,5,0)*1000/L7) -> 6.4 | N7: =IF($B7="","",D7/M7) -> 195.3125 | O7: =IF($B7="","",1-(1-VLOOKUP(E7,'3_FACTORES'!$B$6:$D$12,3,0))*(1-VLOOKUP(F7,'3_FACTORES'!$B$17:$D$22,3,0))*(1-IF(H7>1,'3_FACTORES'!$D$36,0))*(1-'3_FACTORES'!$D$37)*(1-IF(VLOOKUP(I7,'2_HOJA_TECNICA'!$B$6:$K$13,10,0)="SI",'3_FACTORES'!$D$38,0))*(1-IF(K7="SI",'3_FACTORES'!$D$39,0))) -> 0.26128 | P7: =IF($B7="","",N7/(1-O7)) -> 264.39314 | Q7: =IF($B7="","",P7-N7) -> 69.080639 | R7: =IF($B7="","",VLOOKUP(I7,'2_HOJA_TECNICA'!$B$6:$K$13,9,0)) -> 18.9 | S7: =IF($B7="","",P7/R7) -> 13.989055
B8: PT-01 | C8: Vigas principales W24 nave | D8: 1250 | E8: F2 | F8: A1 | G8: R2 | H8: 3 | I8: P03 | J8: 75 | K8: NO | L8: =IF($B8="","",J8+IF(H8=1,VLOOKUP(G8,'3_FACTORES'!$B$27:$E$31,4,0),0)) -> 75 | M8: =IF($B8="","",VLOOKUP(I8,'2_HOJA_TECNICA'!$B$6:$K$13,5,0)*1000/L8) -> 8 | N8: =IF($B8="","",D8/M8) -> 156.25 | O8: =IF($B8="","",1-(1-VLOOKUP(E8,'3_FACTORES'!$B$6:$D$12,3,0))*(1-VLOOKUP(F8,'3_FACTORES'!$B$17:$D$22,3,0))*(1-IF(H8>1,'3_FACTORES'!$D$36,0))*(1-'3_FACTORES'!$D$37)*(1-IF(VLOOKUP(I8,'2_HOJA_TECNICA'!$B$6:$K$13,10,0)="SI",'3_FACTORES'!$D$38,0))*(1-IF(K8="SI",'3_FACTORES'!$D$39,0))) -> 0.26128 | P8: =IF($B8="","",N8/(1-O8)) -> 211.51451 | Q8: =IF($B8="","",P8-N8) -> 55.264512 | R8: =IF($B8="","",VLOOKUP(I8,'2_HOJA_TECNICA'!$B$6:$K$13,9,0)) -> 18.9 | S8: =IF($B8="","",P8/R8) -> 11.191244
B9: PT-02 | C9: Armadura de cubierta (celosía) | D9: 800 | E9: F5 | F9: A1 | G9: R2 | H9: 1 | I9: P01 | J9: 75 | K9: SI | L9: =IF($B9="","",J9+IF(H9=1,VLOOKUP(G9,'3_FACTORES'!$B$27:$E$31,4,0),0)) -> 100 | M9: =IF($B9="","",VLOOKUP(I9,'2_HOJA_TECNICA'!$B$6:$K$13,5,0)*1000/L9) -> 6.2 | N9: =IF($B9="","",D9/M9) -> 129.03226 | O9: =IF($B9="","",1-(1-VLOOKUP(E9,'3_FACTORES'!$B$6:$D$12,3,0))*(1-VLOOKUP(F9,'3_FACTORES'!$B$17:$D$22,3,0))*(1-IF(H9>1,'3_FACTORES'!$D$36,0))*(1-'3_FACTORES'!$D$37)*(1-IF(VLOOKUP(I9,'2_HOJA_TECNICA'!$B$6:$K$13,10,0)="SI",'3_FACTORES'!$D$38,0))*(1-IF(K9="SI",'3_FACTORES'!$D$39,0))) -> 0.497152 | P9: =IF($B9="","",N9/(1-O9)) -> 256.60291 | Q9: =IF($B9="","",P9-N9) -> 127.57065 | R9: =IF($B9="","",VLOOKUP(I9,'2_HOJA_TECNICA'!$B$6:$K$13,9,0)) -> 18.9 | S9: =IF($B9="","",P9/R9) -> 13.576873
B10: PT-02 | C10: Armadura de cubierta (celosía) | D10: 800 | E10: F5 | F10: A1 | G10: R2 | H10: 2 | I10: P03 | J10: 75 | K10: NO | L10: =IF($B10="","",J10+IF(H10=1,VLOOKUP(G10,'3_FACTORES'!$B$27:$E$31,4,0),0)) -> 75 | M10: =IF($B10="","",VLOOKUP(I10,'2_HOJA_TECNICA'!$B$6:$K$13,5,0)*1000/L10) -> 8 | N10: =IF($B10="","",D10/M10) -> 100 | O10: =IF($B10="","",1-(1-VLOOKUP(E10,'3_FACTORES'!$B$6:$D$12,3,0))*(1-VLOOKUP(F10,'3_FACTORES'!$B$17:$D$22,3,0))*(1-IF(H10>1,'3_FACTORES'!$D$36,0))*(1-'3_FACTORES'!$D$37)*(1-IF(VLOOKUP(I10,'2_HOJA_TECNICA'!$B$6:$K$13,10,0)="SI",'3_FACTORES'!$D$38,0))*(1-IF(K10="SI",'3_FACTORES'!$D$39,0))) -> 0.50752 | P10: =IF($B10="","",N10/(1-O10)) -> 203.05393 | Q10: =IF($B10="","",P10-N10) -> 103.05393 | R10: =IF($B10="","",VLOOKUP(I10,'2_HOJA_TECNICA'!$B$6:$K$13,9,0)) -> 18.9 | S10: =IF($B10="","",P10/R10) -> 10.743594
B11: PT-03 | C11: Columnas con protección ignífuga R60 | D11: 600 | E11: F2 | F11: A1 | G11: R4 | H11: 1 | I11: P01 | J11: 75 | K11: SI | L11: =IF($B11="","",J11+IF(H11=1,VLOOKUP(G11,'3_FACTORES'!$B$27:$E$31,4,0),0)) -> 135 | M11: =IF($B11="","",VLOOKUP(I11,'2_HOJA_TECNICA'!$B$6:$K$13,5,0)*1000/L11) -> 4.5925926 | N11: =IF($B11="","",D11/M11) -> 130.64516 | O11: =IF($B11="","",1-(1-VLOOKUP(E11,'3_FACTORES'!$B$6:$D$12,3,0))*(1-VLOOKUP(F11,'3_FACTORES'!$B$17:$D$22,3,0))*(1-IF(H11>1,'3_FACTORES'!$D$36,0))*(1-'3_FACTORES'!$D$37)*(1-IF(VLOOKUP(I11,'2_HOJA_TECNICA'!$B$6:$K$13,10,0)="SI",'3_FACTORES'!$D$38,0))*(1-IF(K11="SI",'3_FACTORES'!$D$39,0))) -> 0.245728 | P11: =IF($B11="","",N11/(1-O11)) -> 173.20696 | Q11: =IF($B11="","",P11-N11) -> 42.5618 | R11: =IF($B11="","",VLOOKUP(I11,'2_HOJA_TECNICA'!$B$6:$K$13,9,0)) -> 18.9 | S11: =IF($B11="","",P11/R11) -> 9.1643895
B12: PT-03 | C12: Columnas ignífugo R60 — INTUMESCENTE EN PLANTA | D12: 600 | E12: F2 | F12: A1 | G12: R4 | H12: 2 | I12: P04 | J12: 700 | K12: NO | L12: =IF($B12="","",J12+IF(H12=1,VLOOKUP(G12,'3_FACTORES'!$B$27:$E$31,4,0),0)) -> 700 | M12: =IF($B12="","",VLOOKUP(I12,'2_HOJA_TECNICA'!$B$6:$K$13,5,0)*1000/L12) -> 0.98571429 | N12: =IF($B12="","",D12/M12) -> 608.69565 | O12: =IF($B12="","",1-(1-VLOOKUP(E12,'3_FACTORES'!$B$6:$D$12,3,0))*(1-VLOOKUP(F12,'3_FACTORES'!$B$17:$D$22,3,0))*(1-IF(H12>1,'3_FACTORES'!$D$36,0))*(1-'3_FACTORES'!$D$37)*(1-IF(VLOOKUP(I12,'2_HOJA_TECNICA'!$B$6:$K$13,10,0)="SI",'3_FACTORES'!$D$38,0))*(1-IF(K12="SI",'3_FACTORES'!$D$39,0))) -> 0.3499264 | P12: =IF($B12="","",N12/(1-O12)) -> 936.34883 | Q12: =IF($B12="","",P12-N12) -> 327.65317 | R12: =IF($B12="","",VLOOKUP(I12,'2_HOJA_TECNICA'!$B$6:$K$13,9,0)) -> 25 | S12: =IF($B12="","",P12/R12) -> 37.453953
B13: PT-03 | C13: Columnas ignífugo R60 — INTUMESCENTE EN SITIO | D13: 600 | E13: F2 | F13: A6 | G13: R4 | H13: 3 | I13: P04 | J13: 300 | K13: NO | L13: =IF($B13="","",J13+IF(H13=1,VLOOKUP(G13,'3_FACTORES'!$B$27:$E$31,4,0),0)) -> 300 | M13: =IF($B13="","",VLOOKUP(I13,'2_HOJA_TECNICA'!$B$6:$K$13,5,0)*1000/L13) -> 2.3 | N13: =IF($B13="","",D13/M13) -> 260.86957 | O13: =IF($B13="","",1-(1-VLOOKUP(E13,'3_FACTORES'!$B$6:$D$12,3,0))*(1-VLOOKUP(F13,'3_FACTORES'!$B$17:$D$22,3,0))*(1-IF(H13>1,'3_FACTORES'!$D$36,0))*(1-'3_FACTORES'!$D$37)*(1-IF(VLOOKUP(I13,'2_HOJA_TECNICA'!$B$6:$K$13,10,0)="SI",'3_FACTORES'!$D$38,0))*(1-IF(K13="SI",'3_FACTORES'!$D$39,0))) -> 0.33548032 | P13: =IF($B13="","",N13/(1-O13)) -> 392.56861 | Q13: =IF($B13="","",P13-N13) -> 131.69904 | R13: =IF($B13="","",VLOOKUP(I13,'2_HOJA_TECNICA'!$B$6:$K$13,9,0)) -> 25 | S13: =IF($B13="","",P13/R13) -> 15.702744
L14: =IF($B14="","",J14+IF(H14=1,VLOOKUP(G14,'3_FACTORES'!$B$27:$E$31,4,0),0)) | M14: =IF($B14="","",VLOOKUP(I14,'2_HOJA_TECNICA'!$B$6:$K$13,5,0)*1000/L14) | N14: =IF($B14="","",D14/M14) | O14: =IF($B14="","",1-(1-VLOOKUP(E14,'3_FACTORES'!$B$6:$D$12,3,0))*(1-VLOOKUP(F14,'3_FACTORES'!$B$17:$D$22,3,0))*(1-IF(H14>1,'3_FACTORES'!$D$36,0))*(1-'3_FACTORES'!$D$37)*(1-IF(VLOOKUP(I14,'2_HOJA_TECNICA'!$B$6:$K$13,10,0)="SI",'3_FACTORES'!$D$38,0))*(1-IF(K14="SI",'3_FACTORES'!$D$39,0))) | P14: =IF($B14="","",N14/(1-O14)) | Q14: =IF($B14="","",P14-N14) | R14: =IF($B14="","",VLOOKUP(I14,'2_HOJA_TECNICA'!$B$6:$K$13,9,0)) | S14: =IF($B14="","",P14/R14)
L15: =IF($B15="","",J15+IF(H15=1,VLOOKUP(G15,'3_FACTORES'!$B$27:$E$31,4,0),0)) | M15: =IF($B15="","",VLOOKUP(I15,'2_HOJA_TECNICA'!$B$6:$K$13,5,0)*1000/L15) | N15: =IF($B15="","",D15/M15) | O15: =IF($B15="","",1-(1-VLOOKUP(E15,'3_FACTORES'!$B$6:$D$12,3,0))*(1-VLOOKUP(F15,'3_FACTORES'!$B$17:$D$22,3,0))*(1-IF(H15>1,'3_FACTORES'!$D$36,0))*(1-'3_FACTORES'!$D$37)*(1-IF(VLOOKUP(I15,'2_HOJA_TECNICA'!$B$6:$K$13,10,0)="SI",'3_FACTORES'!$D$38,0))*(1-IF(K15="SI",'3_FACTORES'!$D$39,0))) | P15: =IF($B15="","",N15/(1-O15)) | Q15: =IF($B15="","",P15-N15) | R15: =IF($B15="","",VLOOKUP(I15,'2_HOJA_TECNICA'!$B$6:$K$13,9,0)) | S15: =IF($B15="","",P15/R15)
L16: =IF($B16="","",J16+IF(H16=1,VLOOKUP(G16,'3_FACTORES'!$B$27:$E$31,4,0),0)) | M16: =IF($B16="","",VLOOKUP(I16,'2_HOJA_TECNICA'!$B$6:$K$13,5,0)*1000/L16) | N16: =IF($B16="","",D16/M16) | O16: =IF($B16="","",1-(1-VLOOKUP(E16,'3_FACTORES'!$B$6:$D$12,3,0))*(1-VLOOKUP(F16,'3_FACTORES'!$B$17:$D$22,3,0))*(1-IF(H16>1,'3_FACTORES'!$D$36,0))*(1-'3_FACTORES'!$D$37)*(1-IF(VLOOKUP(I16,'2_HOJA_TECNICA'!$B$6:$K$13,10,0)="SI",'3_FACTORES'!$D$38,0))*(1-IF(K16="SI",'3_FACTORES'!$D$39,0))) | P16: =IF($B16="","",N16/(1-O16)) | Q16: =IF($B16="","",P16-N16) | R16: =IF($B16="","",VLOOKUP(I16,'2_HOJA_TECNICA'!$B$6:$K$13,9,0)) | S16: =IF($B16="","",P16/R16)
L17: =IF($B17="","",J17+IF(H17=1,VLOOKUP(G17,'3_FACTORES'!$B$27:$E$31,4,0),0)) | M17: =IF($B17="","",VLOOKUP(I17,'2_HOJA_TECNICA'!$B$6:$K$13,5,0)*1000/L17) | N17: =IF($B17="","",D17/M17) | O17: =IF($B17="","",1-(1-VLOOKUP(E17,'3_FACTORES'!$B$6:$D$12,3,0))*(1-VLOOKUP(F17,'3_FACTORES'!$B$17:$D$22,3,0))*(1-IF(H17>1,'3_FACTORES'!$D$36,0))*(1-'3_FACTORES'!$D$37)*(1-IF(VLOOKUP(I17,'2_HOJA_TECNICA'!$B$6:$K$13,10,0)="SI",'3_FACTORES'!$D$38,0))*(1-IF(K17="SI",'3_FACTORES'!$D$39,0))) | P17: =IF($B17="","",N17/(1-O17)) | Q17: =IF($B17="","",P17-N17) | R17: =IF($B17="","",VLOOKUP(I17,'2_HOJA_TECNICA'!$B$6:$K$13,9,0)) | S17: =IF($B17="","",P17/R17)
L18: =IF($B18="","",J18+IF(H18=1,VLOOKUP(G18,'3_FACTORES'!$B$27:$E$31,4,0),0)) | M18: =IF($B18="","",VLOOKUP(I18,'2_HOJA_TECNICA'!$B$6:$K$13,5,0)*1000/L18) | N18: =IF($B18="","",D18/M18) | O18: =IF($B18="","",1-(1-VLOOKUP(E18,'3_FACTORES'!$B$6:$D$12,3,0))*(1-VLOOKUP(F18,'3_FACTORES'!$B$17:$D$22,3,0))*(1-IF(H18>1,'3_FACTORES'!$D$36,0))*(1-'3_FACTORES'!$D$37)*(1-IF(VLOOKUP(I18,'2_HOJA_TECNICA'!$B$6:$K$13,10,0)="SI",'3_FACTORES'!$D$38,0))*(1-IF(K18="SI",'3_FACTORES'!$D$39,0))) | P18: =IF($B18="","",N18/(1-O18)) | Q18: =IF($B18="","",P18-N18) | R18: =IF($B18="","",VLOOKUP(I18,'2_HOJA_TECNICA'!$B$6:$K$13,9,0)) | S18: =IF($B18="","",P18/R18)
L19: =IF($B19="","",J19+IF(H19=1,VLOOKUP(G19,'3_FACTORES'!$B$27:$E$31,4,0),0)) | M19: =IF($B19="","",VLOOKUP(I19,'2_HOJA_TECNICA'!$B$6:$K$13,5,0)*1000/L19) | N19: =IF($B19="","",D19/M19) | O19: =IF($B19="","",1-(1-VLOOKUP(E19,'3_FACTORES'!$B$6:$D$12,3,0))*(1-VLOOKUP(F19,'3_FACTORES'!$B$17:$D$22,3,0))*(1-IF(H19>1,'3_FACTORES'!$D$36,0))*(1-'3_FACTORES'!$D$37)*(1-IF(VLOOKUP(I19,'2_HOJA_TECNICA'!$B$6:$K$13,10,0)="SI",'3_FACTORES'!$D$38,0))*(1-IF(K19="SI",'3_FACTORES'!$D$39,0))) | P19: =IF($B19="","",N19/(1-O19)) | Q19: =IF($B19="","",P19-N19) | R19: =IF($B19="","",VLOOKUP(I19,'2_HOJA_TECNICA'!$B$6:$K$13,9,0)) | S19: =IF($B19="","",P19/R19)
L20: =IF($B20="","",J20+IF(H20=1,VLOOKUP(G20,'3_FACTORES'!$B$27:$E$31,4,0),0)) | M20: =IF($B20="","",VLOOKUP(I20,'2_HOJA_TECNICA'!$B$6:$K$13,5,0)*1000/L20) | N20: =IF($B20="","",D20/M20) | O20: =IF($B20="","",1-(1-VLOOKUP(E20,'3_FACTORES'!$B$6:$D$12,3,0))*(1-VLOOKUP(F20,'3_FACTORES'!$B$17:$D$22,3,0))*(1-IF(H20>1,'3_FACTORES'!$D$36,0))*(1-'3_FACTORES'!$D$37)*(1-IF(VLOOKUP(I20,'2_HOJA_TECNICA'!$B$6:$K$13,10,0)="SI",'3_FACTORES'!$D$38,0))*(1-IF(K20="SI",'3_FACTORES'!$D$39,0))) | P20: =IF($B20="","",N20/(1-O20)) | Q20: =IF($B20="","",P20-N20) | R20: =IF($B20="","",VLOOKUP(I20,'2_HOJA_TECNICA'!$B$6:$K$13,9,0)) | S20: =IF($B20="","",P20/R20)
L21: =IF($B21="","",J21+IF(H21=1,VLOOKUP(G21,'3_FACTORES'!$B$27:$E$31,4,0),0)) | M21: =IF($B21="","",VLOOKUP(I21,'2_HOJA_TECNICA'!$B$6:$K$13,5,0)*1000/L21) | N21: =IF($B21="","",D21/M21) | O21: =IF($B21="","",1-(1-VLOOKUP(E21,'3_FACTORES'!$B$6:$D$12,3,0))*(1-VLOOKUP(F21,'3_FACTORES'!$B$17:$D$22,3,0))*(1-IF(H21>1,'3_FACTORES'!$D$36,0))*(1-'3_FACTORES'!$D$37)*(1-IF(VLOOKUP(I21,'2_HOJA_TECNICA'!$B$6:$K$13,10,0)="SI",'3_FACTORES'!$D$38,0))*(1-IF(K21="SI",'3_FACTORES'!$D$39,0))) | P21: =IF($B21="","",N21/(1-O21)) | Q21: =IF($B21="","",P21-N21) | R21: =IF($B21="","",VLOOKUP(I21,'2_HOJA_TECNICA'!$B$6:$K$13,9,0)) | S21: =IF($B21="","",P21/R21)
L22: =IF($B22="","",J22+IF(H22=1,VLOOKUP(G22,'3_FACTORES'!$B$27:$E$31,4,0),0)) | M22: =IF($B22="","",VLOOKUP(I22,'2_HOJA_TECNICA'!$B$6:$K$13,5,0)*1000/L22) | N22: =IF($B22="","",D22/M22) | O22: =IF($B22="","",1-(1-VLOOKUP(E22,'3_FACTORES'!$B$6:$D$12,3,0))*(1-VLOOKUP(F22,'3_FACTORES'!$B$17:$D$22,3,0))*(1-IF(H22>1,'3_FACTORES'!$D$36,0))*(1-'3_FACTORES'!$D$37)*(1-IF(VLOOKUP(I22,'2_HOJA_TECNICA'!$B$6:$K$13,10,0)="SI",'3_FACTORES'!$D$38,0))*(1-IF(K22="SI",'3_FACTORES'!$D$39,0))) | P22: =IF($B22="","",N22/(1-O22)) | Q22: =IF($B22="","",P22-N22) | R22: =IF($B22="","",VLOOKUP(I22,'2_HOJA_TECNICA'!$B$6:$K$13,9,0)) | S22: =IF($B22="","",P22/R22)
L23: =IF($B23="","",J23+IF(H23=1,VLOOKUP(G23,'3_FACTORES'!$B$27:$E$31,4,0),0)) | M23: =IF($B23="","",VLOOKUP(I23,'2_HOJA_TECNICA'!$B$6:$K$13,5,0)*1000/L23) | N23: =IF($B23="","",D23/M23) | O23: =IF($B23="","",1-(1-VLOOKUP(E23,'3_FACTORES'!$B$6:$D$12,3,0))*(1-VLOOKUP(F23,'3_FACTORES'!$B$17:$D$22,3,0))*(1-IF(H23>1,'3_FACTORES'!$D$36,0))*(1-'3_FACTORES'!$D$37)*(1-IF(VLOOKUP(I23,'2_HOJA_TECNICA'!$B$6:$K$13,10,0)="SI",'3_FACTORES'!$D$38,0))*(1-IF(K23="SI",'3_FACTORES'!$D$39,0))) | P23: =IF($B23="","",N23/(1-O23)) | Q23: =IF($B23="","",P23-N23) | R23: =IF($B23="","",VLOOKUP(I23,'2_HOJA_TECNICA'!$B$6:$K$13,9,0)) | S23: =IF($B23="","",P23/R23)
L24: =IF($B24="","",J24+IF(H24=1,VLOOKUP(G24,'3_FACTORES'!$B$27:$E$31,4,0),0)) | M24: =IF($B24="","",VLOOKUP(I24,'2_HOJA_TECNICA'!$B$6:$K$13,5,0)*1000/L24) | N24: =IF($B24="","",D24/M24) | O24: =IF($B24="","",1-(1-VLOOKUP(E24,'3_FACTORES'!$B$6:$D$12,3,0))*(1-VLOOKUP(F24,'3_FACTORES'!$B$17:$D$22,3,0))*(1-IF(H24>1,'3_FACTORES'!$D$36,0))*(1-'3_FACTORES'!$D$37)*(1-IF(VLOOKUP(I24,'2_HOJA_TECNICA'!$B$6:$K$13,10,0)="SI",'3_FACTORES'!$D$38,0))*(1-IF(K24="SI",'3_FACTORES'!$D$39,0))) | P24: =IF($B24="","",N24/(1-O24)) | Q24: =IF($B24="","",P24-N24) | R24: =IF($B24="","",VLOOKUP(I24,'2_HOJA_TECNICA'!$B$6:$K$13,9,0)) | S24: =IF($B24="","",P24/R24)
L25: =IF($B25="","",J25+IF(H25=1,VLOOKUP(G25,'3_FACTORES'!$B$27:$E$31,4,0),0)) | M25: =IF($B25="","",VLOOKUP(I25,'2_HOJA_TECNICA'!$B$6:$K$13,5,0)*1000/L25) | N25: =IF($B25="","",D25/M25) | O25: =IF($B25="","",1-(1-VLOOKUP(E25,'3_FACTORES'!$B$6:$D$12,3,0))*(1-VLOOKUP(F25,'3_FACTORES'!$B$17:$D$22,3,0))*(1-IF(H25>1,'3_FACTORES'!$D$36,0))*(1-'3_FACTORES'!$D$37)*(1-IF(VLOOKUP(I25,'2_HOJA_TECNICA'!$B$6:$K$13,10,0)="SI",'3_FACTORES'!$D$38,0))*(1-IF(K25="SI",'3_FACTORES'!$D$39,0))) | P25: =IF($B25="","",N25/(1-O25)) | Q25: =IF($B25="","",P25-N25) | R25: =IF($B25="","",VLOOKUP(I25,'2_HOJA_TECNICA'!$B$6:$K$13,9,0)) | S25: =IF($B25="","",P25/R25)
C26: TOTALES | N26: =SUM(N6:N25) -> 1782.418 | P26: =SUM(P6:P25) -> 2704.9836 | Q26: =SUM(Q6:Q25) -> 922.56554

Sheet 5_RESUMEN
B2: RESUMEN DE COMPRA POR PRODUCTO — CUÑETES Y DESPERDICIO
B3: Consolida 4_CALCULO por producto. La compra se redondea a cuñetes completos; el "colchón de compra" es el excedente por redondeo.
B5: ID Prod. | C5: Producto | D5: Litros teóricos | E5: Litros prácticos | F5: Litros desperdicio | G5: % Desp. medio | H5: Cuñete (L) | I5: Cuñetes a comprar | J5: Litros comprados | K5: Colchón redondeo (L) | L5: Costo compra ($)
B6: ='2_HOJA_TECNICA'!B6 -> P01 | C6: =IF(B6="","",'2_HOJA_TECNICA'!C6) -> Primario epóxico rico en zinc | D6: =IF($B6="","",SUMIF('4_CALCULO'!$I$6:$I$25,$B6,'4_CALCULO'!$N$6:$N$25)) -> 461.29032 | E6: =IF($B6="","",SUMIF('4_CALCULO'!$I$6:$I$25,$B6,'4_CALCULO'!$P$6:$P$25)) -> 697.10456 | F6: =IF($B6="","",SUMIF('4_CALCULO'!$I$6:$I$25,$B6,'4_CALCULO'!$Q$6:$Q$25)) -> 235.81424 | G6: =IF(OR($B6="",E6=0),"",F6/E6) -> 0.33827671 | H6: =IF($B6="","",'2_HOJA_TECNICA'!J6) -> 18.9 | I6: =IF(OR($B6="",E6=0),"",ROUNDUP(E6/H6,0)) -> 37 | J6: =IF($B6="","",IF(I6="","",I6*H6)) -> 699.3 | K6: =IF(OR($B6="",I6=""),"",J6-E6) -> 2.1954388 | L6: =IF(OR($B6="",I6=""),"",I6*'2_HOJA_TECNICA'!L6) -> 0
B7: ='2_HOJA_TECNICA'!B7 -> P02 | C7: =IF(B7="","",'2_HOJA_TECNICA'!C7) -> Epóxico poliamida alto sólidos | D7: =IF($B7="","",SUMIF('4_CALCULO'!$I$6:$I$25,$B7,'4_CALCULO'!$N$6:$N$25)) -> 195.3125 | E7: =IF($B7="","",SUMIF('4_CALCULO'!$I$6:$I$25,$B7,'4_CALCULO'!$P$6:$P$25)) -> 264.39314 | F7: =IF($B7="","",SUMIF('4_CALCULO'!$I$6:$I$25,$B7,'4_CALCULO'!$Q$6:$Q$25)) -> 69.080639 | G7: =IF(OR($B7="",E7=0),"",F7/E7) -> 0.26128 | H7: =IF($B7="","",'2_HOJA_TECNICA'!J7) -> 18.9 | I7: =IF(OR($B7="",E7=0),"",ROUNDUP(E7/H7,0)) -> 14 | J7: =IF($B7="","",IF(I7="","",I7*H7)) -> 264.6 | K7: =IF(OR($B7="",I7=""),"",J7-E7) -> 0.20686052 | L7: =IF(OR($B7="",I7=""),"",I7*'2_HOJA_TECNICA'!L7) -> 0
B8: ='2_HOJA_TECNICA'!B8 -> P03 | C8: =IF(B8="","",'2_HOJA_TECNICA'!C8) -> Acabado poliuretano alifático | D8: =IF($B8="","",SUMIF('4_CALCULO'!$I$6:$I$25,$B8,'4_CALCULO'!$N$6:$N$25)) -> 256.25 | E8: =IF($B8="","",SUMIF('4_CALCULO'!$I$6:$I$25,$B8,'4_CALCULO'!$P$6:$P$25)) -> 414.56844 | F8: =IF($B8="","",SUMIF('4_CALCULO'!$I$6:$I$25,$B8,'4_CALCULO'!$Q$6:$Q$25)) -> 158.31844 | G8: =IF(OR($B8="",E8=0),"",F8/E8) -> 0.38188735 | H8: =IF($B8="","",'2_HOJA_TECNICA'!J8) -> 18.9 | I8: =IF(OR($B8="",E8=0),"",ROUNDUP(E8/H8,0)) -> 22 | J8: =IF($B8="","",IF(I8="","",I8*H8)) -> 415.8 | K8: =IF(OR($B8="",I8=""),"",J8-E8) -> 1.2315573 | L8: =IF(OR($B8="",I8=""),"",I8*'2_HOJA_TECNICA'!L8) -> 0
B9: ='2_HOJA_TECNICA'!B9 -> P04 | C9: =IF(B9="","",'2_HOJA_TECNICA'!C9) -> Intumescente base agua | D9: =IF($B9="","",SUMIF('4_CALCULO'!$I$6:$I$25,$B9,'4_CALCULO'!$N$6:$N$25)) -> 869.56522 | E9: =IF($B9="","",SUMIF('4_CALCULO'!$I$6:$I$25,$B9,'4_CALCULO'!$P$6:$P$25)) -> 1328.9174 | F9: =IF($B9="","",SUMIF('4_CALCULO'!$I$6:$I$25,$B9,'4_CALCULO'!$Q$6:$Q$25)) -> 459.35222 | G9: =IF(OR($B9="",E9=0),"",F9/E9) -> 0.34565896 | H9: =IF($B9="","",'2_HOJA_TECNICA'!J9) -> 25 | I9: =IF(OR($B9="",E9=0),"",ROUNDUP(E9/H9,0)) -> 54 | J9: =IF($B9="","",IF(I9="","",I9*H9)) -> 1350 | K9: =IF(OR($B9="",I9=""),"",J9-E9) -> 21.082567 | L9: =IF(OR($B9="",I9=""),"",I9*'2_HOJA_TECNICA'!L9) -> 0
B10: ='2_HOJA_TECNICA'!B10 -> P05 | C10: =IF(B10="","",'2_HOJA_TECNICA'!C10) -> 0 | D10: =IF($B10="","",SUMIF('4_CALCULO'!$I$6:$I$25,$B10,'4_CALCULO'!$N$6:$N$25)) -> 0 | E10: =IF($B10="","",SUMIF('4_CALCULO'!$I$6:$I$25,$B10,'4_CALCULO'!$P$6:$P$25)) -> 0 | F10: =IF($B10="","",SUMIF('4_CALCULO'!$I$6:$I$25,$B10,'4_CALCULO'!$Q$6:$Q$25)) -> 0 | G10: =IF(OR($B10="",E10=0),"",F10/E10) | H10: =IF($B10="","",'2_HOJA_TECNICA'!J10) -> 0 | I10: =IF(OR($B10="",E10=0),"",ROUNDUP(E10/H10,0)) | J10: =IF($B10="","",IF(I10="","",I10*H10)) | K10: =IF(OR($B10="",I10=""),"",J10-E10) | L10: =IF(OR($B10="",I10=""),"",I10*'2_HOJA_TECNICA'!L10)
B11: ='2_HOJA_TECNICA'!B11 -> P06 | C11: =IF(B11="","",'2_HOJA_TECNICA'!C11) -> 0 | D11: =IF($B11="","",SUMIF('4_CALCULO'!$I$6:$I$25,$B11,'4_CALCULO'!$N$6:$N$25)) -> 0 | E11: =IF($B11="","",SUMIF('4_CALCULO'!$I$6:$I$25,$B11,'4_CALCULO'!$P$6:$P$25)) -> 0 | F11: =IF($B11="","",SUMIF('4_CALCULO'!$I$6:$I$25,$B11,'4_CALCULO'!$Q$6:$Q$25)) -> 0 | G11: =IF(OR($B11="",E11=0),"",F11/E11) | H11: =IF($B11="","",'2_HOJA_TECNICA'!J11) -> 0 | I11: =IF(OR($B11="",E11=0),"",ROUNDUP(E11/H11,0)) | J11: =IF($B11="","",IF(I11="","",I11*H11)) | K11: =IF(OR($B11="",I11=""),"",J11-E11) | L11: =IF(OR($B11="",I11=""),"",I11*'2_HOJA_TECNICA'!L11)
B12: ='2_HOJA_TECNICA'!B12 -> P07 | C12: =IF(B12="","",'2_HOJA_TECNICA'!C12) -> 0 | D12: =IF($B12="","",SUMIF('4_CALCULO'!$I$6:$I$25,$B12,'4_CALCULO'!$N$6:$N$25)) -> 0 | E12: =IF($B12="","",SUMIF('4_CALCULO'!$I$6:$I$25,$B12,'4_CALCULO'!$P$6:$P$25)) -> 0 | F12: =IF($B12="","",SUMIF('4_CALCULO'!$I$6:$I$25,$B12,'4_CALCULO'!$Q$6:$Q$25)) -> 0 | G12: =IF(OR($B12="",E12=0),"",F12/E12) | H12: =IF($B12="","",'2_HOJA_TECNICA'!J12) -> 0 | I12: =IF(OR($B12="",E12=0),"",ROUNDUP(E12/H12,0)) | J12: =IF($B12="","",IF(I12="","",I12*H12)) | K12: =IF(OR($B12="",I12=""),"",J12-E12) | L12: =IF(OR($B12="",I12=""),"",I12*'2_HOJA_TECNICA'!L12)
B13: ='2_HOJA_TECNICA'!B13 -> P08 | C13: =IF(B13="","",'2_HOJA_TECNICA'!C13) -> 0 | D13: =IF($B13="","",SUMIF('4_CALCULO'!$I$6:$I$25,$B13,'4_CALCULO'!$N$6:$N$25)) -> 0 | E13: =IF($B13="","",SUMIF('4_CALCULO'!$I$6:$I$25,$B13,'4_CALCULO'!$P$6:$P$25)) -> 0 | F13: =IF($B13="","",SUMIF('4_CALCULO'!$I$6:$I$25,$B13,'4_CALCULO'!$Q$6:$Q$25)) -> 0 | G13: =IF(OR($B13="",E13=0),"",F13/E13) | H13: =IF($B13="","",'2_HOJA_TECNICA'!J13) -> 0 | I13: =IF(OR($B13="",E13=0),"",ROUNDUP(E13/H13,0)) | J13: =IF($B13="","",IF(I13="","",I13*H13)) | K13: =IF(OR($B13="",I13=""),"",J13-E13) | L13: =IF(OR($B13="",I13=""),"",I13*'2_HOJA_TECNICA'!L13)
C14: TOTAL | D14: =SUM(D6:D13) -> 1782.418 | E14: =SUM(E6:E13) -> 2704.9836 | F14: =SUM(F6:F13) -> 922.56554 | I14: =SUM(I6:I13) -> 127 | J14: =SUM(J6:J13) -> 2729.7 | K14: =SUM(K6:K13) -> 24.716423 | L14: =SUM(L6:L13) -> 0

Sheet 6_IGNIFUGO
B2: PINTURA INTUMESCENTE — GUÍA DE MASIVIDAD Hp/A Y CONSIDERACIONES
B4: TABLA ILUSTRATIVA — EPS (µm) según masividad Hp/A y resistencia al fuego (SUSTITUIR por certificado del fabricante)
B5: Hp/A (m⁻¹) | C5: R30 (µm) | D5: R60 (µm) | E5: R90 (µm) | F5: R120 (µm) | G5: Comentario
B6: 50 | C6: 250 | D6: 450 | E6: 900 | F6: 1500 | G6: Secciones muy pesadas: espesores mínimos.
B7: 100 | C7: 300 | D7: 700 | E7: 1400 | F7: 2400 | G7: Rango común de columnas W pesadas.
B8: 150 | C8: 400 | D8: 1000 | E8: 2000 | F8: 3400 | G8: Vigas y columnas medianas.
B9: 200 | C9: 500 | D9: 1300 | E9: 2700 | F9: 4500 | G9: Perfiles ligeros: espesores altos; evaluar mortero proyectado como alternativa.
B10: 260 | C10: 650 | D10: 1700 | E10: 3500 | F10: 6000 | G10: Límite práctico usual de perfiles a proteger con intumescente.
B13: CALCULADORA DE MASIVIDAD Hp/A
B14: Perímetro expuesto Hp (m): | C14: 1.6 | D14: 3 caras o 4 caras según condición de exposición (losa sobre patín superior = 3 caras).
B15: Área de la sección A (m²): | C15: 0.0119
B16: Hp/A (m⁻¹): | C16: =IF(C15=0,"",C14/C15) -> 134.45378
B18: CONSIDERACIONES OBLIGATORIAS PARA INTUMESCENTES
B19: EPS certificado | C19: El espesor NO sale del TDS genérico: sale de la carta de espesores certificada del fabricante (UL 263 / ASTM E119 / EN 13381-8) para el Hp/A de cada perfil y el tiempo R requerido. Zona Humana: validar contra certificado y proyecto.
B20: Primario compatible | C20: Solo primarios aprobados por el fabricante del intumescente (normalmente epóxico o zinc aprobado, 50–75 µm). Un primario no certificado invalida la protección.
B21: Múltiples pasadas | C21: Espesor máximo por pasada típico 400–800 µm húmedo (base agua) — un R60 puede requerir 3–6 pasadas con secado entre ellas. Cada pasada suma pérdidas: por eso la Tabla D aplica el recargo D3.
B22: Ambiente de aplicación | C22: Base agua: aplicar en taller o ambiente controlado (T > 10 °C, HR < 80%, sustrato 3 °C sobre punto de rocío). Exterior sin control = riesgo de lavado por lluvia antes de curar.
B23: Sellador / top coat | C23: En exposición exterior o C3+, el intumescente requiere sello de acabado aprobado; incluirlo como capa adicional en 4_CALCULO.
B24: Densidad y rendimiento | C24: Los intumescentes rinden poco (SV 65–72%, EPS enormes): 1 m² a 1,000 µm consume ≈1.4–1.5 L teóricos. El costo por m² domina el APU: cotizar por Hp/A real, nunca con EPS promedio.
B25: Medición y trazabilidad | C25: Registrar EPS por pasada (SSPC-PA 2 nivel por elemento); el cliente/DRO exige el registro para liberar. Reproceso por espesor bajo = más consumo no presupuestado si no se controla.
B26: Malla de refuerzo | C26: Espesores > ~3,000 µm o secciones críticas pueden requerir malla de refuerzo según fabricante: costo y HH adicionales fuera de este módulo.
B28: REPARTO PLANTA / SITIO DEL INTUMESCENTE (asistente de captura)
B29: El intumescente casi nunca se termina en planta: lo usual es aplicar el grueso del espesor en taller (ambiente controlado, mejor rendimiento) y completar en sitio las últimas manos, los retoques de montaje y las zonas de conexión. Capture aquí el reparto y el asistente le da el EPS de cada porción; luego capture DOS filas en 4_CALCULO para la misma partida: la porción PLANTA con ambiente A1 y la porción SITIO con ambiente A4 o A6. El modelo aplicará automáticamente el mayor desperdicio de obra (viento, condiciones, brocha) y el APU puede cargar la HH de obra más alta. El ejemplo PT-03 de 4_CALCULO ya está capturado así.
B31: EPS total requerido (µm): | C31: 1000 | D31: Reparto típico: 60–80% en planta. Deje más al sitio si habrá mucho daño de transporte/montaje o si las conexiones son de campo.
B32: % del EPS aplicado en PLANTA: | C32: 0.7
B33: EPS a capturar como fila PLANTA (A1): | C33: =C31*C32 -> 700
B34: EPS a capturar como fila SITIO (A4/A6): | C34: =C31*(1-C32) -> 300
B36: Rendimientos distintos planta vs. obra (para el APU): el mismo aplicador rinde en obra entre 40% y 60% de lo que rinde en planta (andamios, clima, logística de materiales, esperas de secado a la intemperie). Capture la partida de sitio con HH/m² propia en 11_APU o cargue la diferencia como partida separada. La pintura también rinde menos: eso ya lo captura el ambiente A4/A6 en la fila de sitio.

Sheet 7_ABRASIVO
B2: CONSUMO DE ABRASIVO — ARENA (SANDBLASTING) Y GRANALLA (SHOT BLASTING)
B3: La arena es de UN SOLO USO (a cielo abierto no se recupera; se contamina y fragmenta). La granalla de acero RECIRCULA en máquina o cuarto de recuperación: el consumo neto es solo la merma por atrición, fugas y limpieza. Calibre los valores en amarillo con datos de planta.
B5: TABLA E — PARÁMETROS DEL ABRASIVO (consumo bruto por grado de limpieza + desperdicio más probable)
B6: Código | C6: Abrasivo / Sistema | E6: Consumo SP6 (kg/m²) | F6: Consumo SP10 (kg/m²) | G6: Consumo SP5 (kg/m²) | H6: % Desperdicio probable | I6: Presentación (kg) | J6: Precio ($/presentación) | N6: Criterio
B7: AB1 | C7: Arena sílica / mineral — sandblasting a cielo abierto | E7: 30 | F7: 45 | G7: 55 | H7: 0.15 | I7: 1500 | J7: 0 | N7: Un solo uso. El consumo bruto ya incluye que no se recupera; el desperdicio adicional (15%) cubre humedad, derrames, fondo de sacos/súper sacos y arena no aprovechable del lote. Perfil obtenido más irregular. Restricciones de sílice libre (NOM-010-STPS): considerar escoria de cobre/níquel como sustituto con consumos similares.
B8: AB2 | C8: Granalla de acero (shot/grit) — máquina de granallado con recuperación | E8: 0.35 | F8: 0.55 | G8: 0.75 | H8: 0.08 | I8: 25 | J8: 0 | N8: Recircula 150–250 ciclos: el consumo neto es la REPOSICIÓN por atrición (desgaste del grano) + finos extraídos por el separador. El desperdicio adicional (8%) cubre fugas de sellos, granalla atrapada en cajones/perfiles tubulares que se va con la pieza, derrames y purgas de mezcla operativa.
B9: AB3 | C9: Granalla de acero — cuarto de blasteo manual con recuperación parcial | E9: 1.2 | F9: 1.8 | G9: 2.4 | H9: 0.2 | I9: 25 | J9: 0 | N9: Recuperación por barrido/tornillo sinfín menos eficiente que máquina: más pérdida por mezcla con óxido/cascarilla y granalla que sale en las piezas. Desperdicio 20% sobre la reposición.
B10: Presentación: arena en súper saco (1,500 kg típico) o granel; granalla en saco de 25 kg. Ajuste según su proveedor. Los consumos por m² dependen de la condición inicial del acero (grado de oxidación A–D según ISO 8501-1): los valores precargados asumen condición B–C típica de perfil comercial.
B12: CÁLCULO DE ABRASIVO POR PARTIDA
B13: Partida | C13: Descripción | D13: Área (m²) | E13: Abrasivo (AB1-AB3) | F13: Grado limpieza (SP6/SP10/SP5) | G13: Consumo base (kg/m²) | H13: Kg teóricos | I13: % Desperdicio | J13: Kg totales | K13: Presentación (kg) | L13: Presentaciones a comprar | M13: Kg comprados | N13: Costo ($) | O13: Condición (A-D)
B14: PT-01 | C14: Vigas principales W24 nave | D14: 1250 | E14: AB2 | F14: SP10 | G14: =IF($B14="","",VLOOKUP(E14,$B$7:$J$9,IF(F14="SP6",4,IF(F14="SP10",5,6)),0)*IF(O14="",1,VLOOKUP(O14,$B$33:$E$36,4,0))) -> 0.55 | H14: =IF($B14="","",D14*G14) -> 687.5 | I14: =IF($B14="","",VLOOKUP(E14,$B$7:$J$9,7,0)) -> 0.08 | J14: =IF($B14="","",H14*(1+I14)) -> 742.5 | K14: =IF($B14="","",VLOOKUP(E14,$B$7:$J$9,8,0)) -> 25 | L14: =IF($B14="","",ROUNDUP(J14/K14,0)) -> 30 | M14: =IF($B14="","",L14*K14) -> 750 | N14: =IF($B14="","",L14*VLOOKUP(E14,$B$7:$J$9,9,0)) -> 0 | O14: B
B15: PT-02 | C15: Armadura de cubierta (celosía) | D15: 800 | E15: AB3 | F15: SP10 | G15: =IF($B15="","",VLOOKUP(E15,$B$7:$J$9,IF(F15="SP6",4,IF(F15="SP10",5,6)),0)*IF(O15="",1,VLOOKUP(O15,$B$33:$E$36,4,0))) -> 2.52 | H15: =IF($B15="","",D15*G15) -> 2016 | I15: =IF($B15="","",VLOOKUP(E15,$B$7:$J$9,7,0)) -> 0.2 | J15: =IF($B15="","",H15*(1+I15)) -> 2419.2 | K15: =IF($B15="","",VLOOKUP(E15,$B$7:$J$9,8,0)) -> 25 | L15: =IF($B15="","",ROUNDUP(J15/K15,0)) -> 97 | M15: =IF($B15="","",L15*K15) -> 2425 | N15: =IF($B15="","",L15*VLOOKUP(E15,$B$7:$J$9,9,0)) -> 0 | O15: C
B16: PT-03 | C16: Columnas con protección ignífuga R60 | D16: 600 | E16: AB2 | F16: SP10 | G16: =IF($B16="","",VLOOKUP(E16,$B$7:$J$9,IF(F16="SP6",4,IF(F16="SP10",5,6)),0)*IF(O16="",1,VLOOKUP(O16,$B$33:$E$36,4,0))) -> 0.715 | H16: =IF($B16="","",D16*G16) -> 429 | I16: =IF($B16="","",VLOOKUP(E16,$B$7:$J$9,7,0)) -> 0.08 | J16: =IF($B16="","",H16*(1+I16)) -> 463.32 | K16: =IF($B16="","",VLOOKUP(E16,$B$7:$J$9,8,0)) -> 25 | L16: =IF($B16="","",ROUNDUP(J16/K16,0)) -> 19 | M16: =IF($B16="","",L16*K16) -> 475 | N16: =IF($B16="","",L16*VLOOKUP(E16,$B$7:$J$9,9,0)) -> 0 | O16: A
G17: =IF($B17="","",VLOOKUP(E17,$B$7:$J$9,IF(F17="SP6",4,IF(F17="SP10",5,6)),0)*IF(O17="",1,VLOOKUP(O17,$B$33:$E$36,4,0))) | H17: =IF($B17="","",D17*G17) | I17: =IF($B17="","",VLOOKUP(E17,$B$7:$J$9,7,0)) | J17: =IF($B17="","",H17*(1+I17)) | K17: =IF($B17="","",VLOOKUP(E17,$B$7:$J$9,8,0)) | L17: =IF($B17="","",ROUNDUP(J17/K17,0)) | M17: =IF($B17="","",L17*K17) | N17: =IF($B17="","",L17*VLOOKUP(E17,$B$7:$J$9,9,0))
G18: =IF($B18="","",VLOOKUP(E18,$B$7:$J$9,IF(F18="SP6",4,IF(F18="SP10",5,6)),0)*IF(O18="",1,VLOOKUP(O18,$B$33:$E$36,4,0))) | H18: =IF($B18="","",D18*G18) | I18: =IF($B18="","",VLOOKUP(E18,$B$7:$J$9,7,0)) | J18: =IF($B18="","",H18*(1+I18)) | K18: =IF($B18="","",VLOOKUP(E18,$B$7:$J$9,8,0)) | L18: =IF($B18="","",ROUNDUP(J18/K18,0)) | M18: =IF($B18="","",L18*K18) | N18: =IF($B18="","",L18*VLOOKUP(E18,$B$7:$J$9,9,0))
G19: =IF($B19="","",VLOOKUP(E19,$B$7:$J$9,IF(F19="SP6",4,IF(F19="SP10",5,6)),0)*IF(O19="",1,VLOOKUP(O19,$B$33:$E$36,4,0))) | H19: =IF($B19="","",D19*G19) | I19: =IF($B19="","",VLOOKUP(E19,$B$7:$J$9,7,0)) | J19: =IF($B19="","",H19*(1+I19)) | K19: =IF($B19="","",VLOOKUP(E19,$B$7:$J$9,8,0)) | L19: =IF($B19="","",ROUNDUP(J19/K19,0)) | M19: =IF($B19="","",L19*K19) | N19: =IF($B19="","",L19*VLOOKUP(E19,$B$7:$J$9,9,0))
G20: =IF($B20="","",VLOOKUP(E20,$B$7:$J$9,IF(F20="SP6",4,IF(F20="SP10",5,6)),0)*IF(O20="",1,VLOOKUP(O20,$B$33:$E$36,4,0))) | H20: =IF($B20="","",D20*G20) | I20: =IF($B20="","",VLOOKUP(E20,$B$7:$J$9,7,0)) | J20: =IF($B20="","",H20*(1+I20)) | K20: =IF($B20="","",VLOOKUP(E20,$B$7:$J$9,8,0)) | L20: =IF($B20="","",ROUNDUP(J20/K20,0)) | M20: =IF($B20="","",L20*K20) | N20: =IF($B20="","",L20*VLOOKUP(E20,$B$7:$J$9,9,0))
G21: =IF($B21="","",VLOOKUP(E21,$B$7:$J$9,IF(F21="SP6",4,IF(F21="SP10",5,6)),0)*IF(O21="",1,VLOOKUP(O21,$B$33:$E$36,4,0))) | H21: =IF($B21="","",D21*G21) | I21: =IF($B21="","",VLOOKUP(E21,$B$7:$J$9,7,0)) | J21: =IF($B21="","",H21*(1+I21)) | K21: =IF($B21="","",VLOOKUP(E21,$B$7:$J$9,8,0)) | L21: =IF($B21="","",ROUNDUP(J21/K21,0)) | M21: =IF($B21="","",L21*K21) | N21: =IF($B21="","",L21*VLOOKUP(E21,$B$7:$J$9,9,0))
G22: =IF($B22="","",VLOOKUP(E22,$B$7:$J$9,IF(F22="SP6",4,IF(F22="SP10",5,6)),0)*IF(O22="",1,VLOOKUP(O22,$B$33:$E$36,4,0))) | H22: =IF($B22="","",D22*G22) | I22: =IF($B22="","",VLOOKUP(E22,$B$7:$J$9,7,0)) | J22: =IF($B22="","",H22*(1+I22)) | K22: =IF($B22="","",VLOOKUP(E22,$B$7:$J$9,8,0)) | L22: =IF($B22="","",ROUNDUP(J22/K22,0)) | M22: =IF($B22="","",L22*K22) | N22: =IF($B22="","",L22*VLOOKUP(E22,$B$7:$J$9,9,0))
G23: =IF($B23="","",VLOOKUP(E23,$B$7:$J$9,IF(F23="SP6",4,IF(F23="SP10",5,6)),0)*IF(O23="",1,VLOOKUP(O23,$B$33:$E$36,4,0))) | H23: =IF($B23="","",D23*G23) | I23: =IF($B23="","",VLOOKUP(E23,$B$7:$J$9,7,0)) | J23: =IF($B23="","",H23*(1+I23)) | K23: =IF($B23="","",VLOOKUP(E23,$B$7:$J$9,8,0)) | L23: =IF($B23="","",ROUNDUP(J23/K23,0)) | M23: =IF($B23="","",L23*K23) | N23: =IF($B23="","",L23*VLOOKUP(E23,$B$7:$J$9,9,0))
G24: =IF($B24="","",VLOOKUP(E24,$B$7:$J$9,IF(F24="SP6",4,IF(F24="SP10",5,6)),0)*IF(O24="",1,VLOOKUP(O24,$B$33:$E$36,4,0))) | H24: =IF($B24="","",D24*G24) | I24: =IF($B24="","",VLOOKUP(E24,$B$7:$J$9,7,0)) | J24: =IF($B24="","",H24*(1+I24)) | K24: =IF($B24="","",VLOOKUP(E24,$B$7:$J$9,8,0)) | L24: =IF($B24="","",ROUNDUP(J24/K24,0)) | M24: =IF($B24="","",L24*K24) | N24: =IF($B24="","",L24*VLOOKUP(E24,$B$7:$J$9,9,0))
G25: =IF($B25="","",VLOOKUP(E25,$B$7:$J$9,IF(F25="SP6",4,IF(F25="SP10",5,6)),0)*IF(O25="",1,VLOOKUP(O25,$B$33:$E$36,4,0))) | H25: =IF($B25="","",D25*G25) | I25: =IF($B25="","",VLOOKUP(E25,$B$7:$J$9,7,0)) | J25: =IF($B25="","",H25*(1+I25)) | K25: =IF($B25="","",VLOOKUP(E25,$B$7:$J$9,8,0)) | L25: =IF($B25="","",ROUNDUP(J25/K25,0)) | M25: =IF($B25="","",L25*K25) | N25: =IF($B25="","",L25*VLOOKUP(E25,$B$7:$J$9,9,0))
G26: =IF($B26="","",VLOOKUP(E26,$B$7:$J$9,IF(F26="SP6",4,IF(F26="SP10",5,6)),0)*IF(O26="",1,VLOOKUP(O26,$B$33:$E$36,4,0))) | H26: =IF($B26="","",D26*G26) | I26: =IF($B26="","",VLOOKUP(E26,$B$7:$J$9,7,0)) | J26: =IF($B26="","",H26*(1+I26)) | K26: =IF($B26="","",VLOOKUP(E26,$B$7:$J$9,8,0)) | L26: =IF($B26="","",ROUNDUP(J26/K26,0)) | M26: =IF($B26="","",L26*K26) | N26: =IF($B26="","",L26*VLOOKUP(E26,$B$7:$J$9,9,0))
G27: =IF($B27="","",VLOOKUP(E27,$B$7:$J$9,IF(F27="SP6",4,IF(F27="SP10",5,6)),0)*IF(O27="",1,VLOOKUP(O27,$B$33:$E$36,4,0))) | H27: =IF($B27="","",D27*G27) | I27: =IF($B27="","",VLOOKUP(E27,$B$7:$J$9,7,0)) | J27: =IF($B27="","",H27*(1+I27)) | K27: =IF($B27="","",VLOOKUP(E27,$B$7:$J$9,8,0)) | L27: =IF($B27="","",ROUNDUP(J27/K27,0)) | M27: =IF($B27="","",L27*K27) | N27: =IF($B27="","",L27*VLOOKUP(E27,$B$7:$J$9,9,0))
G28: =IF($B28="","",VLOOKUP(E28,$B$7:$J$9,IF(F28="SP6",4,IF(F28="SP10",5,6)),0)*IF(O28="",1,VLOOKUP(O28,$B$33:$E$36,4,0))) | H28: =IF($B28="","",D28*G28) | I28: =IF($B28="","",VLOOKUP(E28,$B$7:$J$9,7,0)) | J28: =IF($B28="","",H28*(1+I28)) | K28: =IF($B28="","",VLOOKUP(E28,$B$7:$J$9,8,0)) | L28: =IF($B28="","",ROUNDUP(J28/K28,0)) | M28: =IF($B28="","",L28*K28) | N28: =IF($B28="","",L28*VLOOKUP(E28,$B$7:$J$9,9,0))
C29: TOTALES | H29: =SUM(H14:H28) -> 3132.5 | J29: =SUM(J14:J28) -> 3625.02 | M29: =SUM(M14:M28) -> 3650 | N29: =SUM(N14:N28) -> 0
B31: TABLA F — CONDICIÓN INICIAL DEL ACERO (ISO 8501-1): MULTIPLICADOR DE CONSUMO DE ABRASIVO
B32: Grado | C32: Condición del acero | E32: Multiplicador | N32: Efecto en consumo y en el PERFIL DE ANCLAJE
B33: A | C33: ACERO NUEVO con calamina (cascarilla de laminación) intacta y adherida | E33: 1.3 | N33: Aunque el perfil sea "nuevo", la calamina es DURA y está bien pegada: arrancarla consume más abrasivo que un acero ligeramente oxidado, y exige granalla ANGULAR (grit) o mezcla con alto % de grit — el shot esférico solo la pule. Si no se corta la calamina, tampoco se genera perfil de anclaje sobre el metal base: se estaría midiendo perfil sobre cascarilla que se desprenderá con la pintura encima.
B34: B | C34: ACERO NUEVO intemperizado: la calamina empieza a desprenderse, óxido superficial ligero | E34: 1 | N34: La condición BASE de las tablas de consumo (el perfil comercial típico llega así). La calamina parcialmente suelta se remueve fácil y el perfil especificado se logra en una pasada normal.
B35: C | C35: ACERO VIEJO oxidado: la calamina ya se cayó por corrosión, óxido general, picaduras apenas visibles | E35: 1.4 | N35: El óxido empaca y "amortigua" el impacto del abrasivo, y contamina la mezcla operativa de la granalladora (los finos de óxido hay que purgarlos: más reposición). El perfil se logra, pero la limpieza exige más pasadas para el mismo grado SP.
B36: D | C36: ACERO VIEJO picado: corrosión con picaduras (pitting) visibles en toda la superficie | E36: 1.9 | N36: El peor caso: sacar el óxido del fondo de cada picadura consume mucho abrasivo y tiempo. OJO CON EL PERFIL: las picaduras generan una rugosidad propia que suele EXCEDER el perfil especificado — mida el perfil real con cinta Testex y use R3/R4 en la Tabla C de 3_FACTORES, porque el volumen muerto será mayor y la capa 1 consumirá más primario. En picaduras profundas puede requerirse capa barrera adicional (surface tolerant) o espesor extra de primario: acordarlo con el cliente antes de cotizar.
B38: Si desconoce la condición, inspeccione el material en patio ANTES de cotizar el blasteo: la diferencia entre B y D casi duplica el abrasivo y las horas de máquina. En proyectos de rehabilitación/reforzamiento (acero en servicio), asuma C o D salvo evidencia en contrario. La condición se captura por partida en la columna O del cálculo de arriba; si se deja vacía, el modelo asume B (multiplicador 1.00).

Sheet 8_GLOSARIO
B2: GLOSARIO DE TÉRMINOS TÉCNICOS Y ABREVIACIONES
B4: — PINTURA Y SISTEMA —
B5: TDS | C5: Technical Data Sheet (hoja técnica): documento del fabricante con % sólidos, EPS recomendado, rendimiento, diluyente, pot-life, tiempos de repintado y condiciones de aplicación.
B6: % SV | C6: Sólidos por Volumen: fracción del volumen de la pintura líquida que queda como película seca tras evaporar solventes. Base de la fórmula de rendimiento.
B7: EPS | C7: Espesor de Película Seca (DFT — Dry Film Thickness): espesor de la pintura ya curada, medido en micras (µm). Es lo que especifica el proyecto y se mide con medidor magnético/eddy current.
B8: EPH | C8: Espesor de Película Húmeda (WFT — Wet Film Thickness): espesor recién aplicado, medido con peine. EPH = EPS / %SV (sin dilución). Control en línea durante la aplicación.
B9: µm (micra) | C9: Micrómetro: milésima de milímetro. 1 mil (milésima de pulgada) = 25.4 µm.
B10: Rendimiento teórico | C10: m² que cubre 1 litro al EPS especificado sin ninguna pérdida: %SV × 1000 / EPS(µm). El rendimiento práctico es siempre menor por los factores de desperdicio.
B11: Cuñete | C11: Envase estándar de pintura, típicamente de 5 galones ≈ 18.9 L (o 19 L nominal). Algunos intumescentes vienen en 20–25 L o por peso.
B12: Volumen muerto | C12: Pintura de la primera capa que "rellena" los valles del perfil de anclaje y no aporta espesor sobre los picos. Se compensa sumando µm extra al EPS de la capa 1.
B13: Franjeo (stripe coat) | C13: Capa adicional aplicada a brocha/rodillo sobre cantos, aristas, soldaduras y tornillería, donde la pintura se retrae y el espesor queda bajo. Exigida por buenas prácticas ISO 12944 en C3+.
B14: Overspray | C14: Pintura atomizada que no se deposita en la pieza y se pierde en el aire. Función de la geometría de la pieza, el método y el viento.
B15: Eficiencia de transferencia | C15: % de la pintura atomizada que efectivamente se deposita: airless 70–80%, convencional 45–60%, brocha/rodillo >95%.
B16: Pot-life | C16: Tiempo útil de la mezcla en productos de dos componentes (2K) después de catalizar. Mezcla no aplicada dentro del pot-life = desperdicio directo.
... B19: C1–C5 / ISO 12944 | C19: Categorías de corrosividad atmosférica: C1 interior seco … C5 industrial/marino severo. Determinan el sistema y los espesores.
B20: — PREPARACIÓN DE SUPERFICIE —
B21: SSPC | C21: The Society for Protective Coatings (hoy AMPP, fusionada con NACE): emite los estándares de preparación de superficie y aplicación más usados en acero estructural.
B22: SP2 / SP3 | C22: Limpieza manual (SP2) y mecánica con herramienta eléctrica (SP3): remueven óxido suelto pero no generan perfil de anclaje.
B23: SP6 | C23: Blast comercial: remueve toda cascarilla y óxido, admite sombras/manchas en ≤33% de cada área unitaria. Equivalente ISO 8501-1: Sa 2.
B24: SP10 | C24: Blast a metal casi blanco (near-white): admite sombras en ≤5%. Equivalente Sa 2½. El grado más especificado en estructura con sistemas de alto desempeño.
B25: SP5 | C25: Blast a metal blanco: superficie 100% libre de contaminantes visibles. Equivalente Sa 3. Para servicios de inmersión o intumescentes exigentes.
B26: Perfil de anclaje | C26: Rugosidad (altura pico-valle en µm) que el abrasivo genera en el acero para que la pintura ancle mecánicamente. Se mide con cinta réplica (Testex) o rugosímetro. Cada primario especifica un rango (típico 40–75 µm).
B27: ISO 8501-1 | C27: Norma que define los grados de oxidación inicial del acero (A: cascarilla intacta … D: picaduras) y los grados de limpieza Sa. La condición inicial afecta el consumo de abrasivo.
B28: SSPC-PA 2 | C28: Estándar de medición de EPS: define número de lecturas por área, promedios y tolerancias para aceptar el espesor aplicado.
B29: Punto de rocío | C29: Temperatura a la que condensa la humedad. Regla: el sustrato debe estar ≥3 °C por encima del punto de rocío para pintar o blastear; si no, se oxida instantáneo (flash rust).
B30: — ABRASIVOS —
B31: Sandblasting | C31: Limpieza con chorro de arena (u otro abrasivo mineral) proyectado con aire comprimido, típicamente a cielo abierto o en cuarto. El abrasivo mineral se fragmenta al impacto: un solo uso.
B32: Shot blasting | C32: Granallado con turbinas u ollas que proyectan granalla de acero; en máquinas con sistema de recuperación, la granalla recircula 150–250 ciclos y solo se repone la merma.
B33: Granalla shot | C33: Grano esférico de acero: martilla y compacta la superficie, genera perfil redondeado. Menos agresiva; buena para cascarilla.
B34: Granalla grit | C34: Grano angular de acero (o mezcla operativa shot+grit): corta y genera perfil angular más profundo, preferido para anclar primarios de alto espesor e intumescentes.
B35: Mezcla operativa | C35: Distribución de tamaños de granalla que se estabiliza en la máquina tras varios ciclos (granos nuevos + parcialmente desgastados). Determina el perfil real obtenido; se controla con reposiciones periódicas.
B36: Atrición | C36: Desgaste y fractura progresiva del grano de granalla en cada ciclo. Es el consumo "real" del shot blasting: kg repuestos por m² procesado.
B37: Escoria de cobre/níquel | C37: Abrasivo mineral sustituto de la arena sílica, sin sílice libre (menor riesgo de silicosis). Consumos similares a la arena; un solo uso o muy pocas reutilizaciones.
B38: NOM-010-STPS | C38: Norma mexicana de agentes químicos contaminantes en el trabajo: restringe el uso de arena sílica en blasteo por el riesgo de silicosis; favorece escoria o granalla.
B39: — IGNÍFUGOS —
B40: Intumescente | C40: Pintura que al exponerse al fuego se expande 30–50 veces formando una espuma carbonosa aislante que retrasa el calentamiento del acero.
B41: Hp/A (masividad) | C41: Relación perímetro expuesto al fuego (Hp, m) entre área de la sección (A, m²), en m⁻¹. A mayor Hp/A, más rápido se calienta el perfil y más espesor de intumescente requiere.
B42: R30/R60/R90/R120 | C42: Resistencia al fuego requerida en minutos: tiempo que el acero debe mantenerse bajo su temperatura crítica (~500–620 °C).
B43: UL 263 / ASTM E119 / EN 13381-8 | C43: Estándares de ensayo con los que el fabricante certifica la carta de espesores del intumescente por masividad y tiempo R.
B44: Temperatura crítica | C44: Temperatura a la que el acero pierde la capacidad portante de diseño (típicamente ~540 °C). Base del dimensionamiento de la protección.
B45: — PRESUPUESTO —
B46: APU | C46: Análisis de Precio Unitario: descomposición del precio por unidad (m², ton, kg) en materiales, mano de obra, equipo e indirectos. Este módulo alimenta el renglón de materiales de pintura y blasteo.
B47: HH/ton | C47: Horas-hombre por tonelada: el driver de mano de obra del motor de presupuesto de METALITEC. La pintura se presupuesta por m², no por ton — de ahí este módulo separado.
B48: Colchón de redondeo | C48: Litros o kg comprados por encima del consumo práctico, por redondear a envases/presentaciones completas. Queda como inventario o merma según manejo de almacén.
B49: DFT/WFT | C49: Siglas en inglés de EPS/EPH; aparecen así en la mayoría de los TDS.
B51: — ESTIMACIÓN DE ÁREA —
B52: Superficie específica (m²/ton) | C52: Metros cuadrados de superficie de acero por cada tonelada. Fórmula rápida: m²/ton ≈ 255 / espesor promedio (mm), derivada de la densidad del acero (7,850 kg/m³) y las dos caras de la lámina equivalente. Rango típico en estructura: 12–45 m²/ton.
B53: Espesor promedio del proyecto | C53: Espesor equivalente ponderado por peso de todos los perfiles y placas del proyecto, en mm. Determina la superficie específica: proyectos de perfil ligero tienen espesor promedio bajo y mucha área por tonelada.
B54: Área pintable | C54: Área total de acero MENOS las superficies que el proyecto excluye de pintura: interior de HSS cerrados, caras embebidas/en contacto con concreto, superficies de fricción de conexiones slip-critical, zonas de soldadura de campo y patines que reciben conectores de cortante.
B55: Superficie de fricción (slip-critical) | C55: Cara de contacto de una conexión atornillada que trabaja por fricción: debe entregarse sin pintura o con recubrimiento certificado clase A/B (RCSC). Pintarla con el sistema normal es una no conformidad.
B57: — CONDICIÓN INICIAL DEL ACERO —
B58: Grados A/B/C/D (ISO 8501-1) | C58: Condición inicial del acero antes de blastear: A = calamina intacta (acero nuevo), B = calamina desprendiéndose, C = óxido general sin picaduras visibles, D = óxido con picaduras. Determina el consumo de abrasivo (multiplicadores de la Tabla F en 7_ABRASIVO) y puede alterar el perfil de anclaje real.
B59: Calamina (cascarilla de laminación) | C59: Capa dura de óxidos que se forma sobre el perfil durante el laminado en caliente. Está bien adherida pero tarde o temprano se desprende: pintar sobre ella es falla segura. Removerla exige granalla angular y más consumo que un óxido ligero.
B60: Picadura (pitting) | C60: Cavidad puntual dejada por la corrosión en acero viejo. Encarece el blasteo (limpiar el fondo de cada hoyo), genera rugosidad extra que aumenta el volumen muerto del primario, y puede requerir tratamiento adicional acordado con el cliente.
B61: Acero surface tolerant | C61: Recubrimiento formulado para tolerar preparación de superficie limitada o sustratos irregulares (acero viejo picado); alternativa cuando no es viable llegar al grado SP especificado en rehabilitaciones.

Sheet 9_CONCEPTOS
B2: CONCEPTOS EXPLICADOS EN LENGUAJE SENCILLO
B3: Explicaciones pensadas para todo el equipo: aplicadores, supervisores, compras y ventas. No hace falta ser ingeniero para entenderlas.
B5: — LO BÁSICO —
B6: ¿Qué es el factor de forma? | C6: Imagine que pinta una pared con un aspersor: casi toda la pintura cae en la pared. Ahora imagine pintar la reja del jardín con el mismo aspersor: gran parte de la pintura pasa entre los barrotes y se pierde en el aire. Eso es el factor de forma: qué tanto de la pintura que sale de la pistola realmente cae sobre la pieza, según su geometría. Una placa ancha aprovecha casi todo (perdemos ~5%); una celosía o armadura, que es puro hueco, desperdicia hasta el 40%. Por eso es lo primero que preguntamos al presupuestar: no cuesta lo mismo pintar 100 m² de placa que 100 m² de celosía, aunque el área sea la misma.
B7: ¿Por qué importa para el desperdicio? | C7: Porque el desperdicio por forma es el más grande de todos y no se puede eliminar: es física, no descuido del pintor. Si lo ignoramos, compramos menos pintura de la necesaria (paros y compras de emergencia) o cotizamos barato y perdemos dinero. Al clasificar cada pieza por su forma (F1 a F7 en la hoja 3_FACTORES), el desperdicio queda calculado y defendible ante el cliente.
B8: Limpieza vs. perfil de anclaje: no son lo mismo | C8: La LIMPIEZA es qué tan libre de óxido, cascarilla y suciedad queda el acero: se ve a simple vista y se compara contra fotos patrón (SP6, SP10, SP5). El PERFIL DE ANCLAJE es la rugosidad que el chorro de abrasivo deja en el metal: pequeños picos y valles, como una lija, que no se aprecian a ojo — se miden con una cinta especial (Testex) en micras. Son dos requisitos distintos: puede tener el acero limpísimo pero liso (la pintura no agarra y se desprende), o rugoso pero sucio (la pintura agarra sobre el óxido y falla igual). El proyecto siempre pide los DOS: por ejemplo "SP10 con perfil de 50–75 µm".
B9: ¿Qué es un mils? | C9: Es una unidad de espesor usada en Estados Unidos: una milésima de pulgada. Como muchas hojas técnicas vienen en mils y otras en micras, hay que saber convertir: 1 mils = 25.4 micras (µm). Regla rápida: mils × 25 ≈ micras. Ejemplo: un primario de 3 mils son ~75 µm; un sistema de 8 mils son ~200 µm. Para referencia, una hoja de papel tiene ~100 µm (4 mils): un sistema de pintura completo es como dos hojas de papel de grueso.
B10: ¿Qué es una pintura epóxica? | C10: Es una pintura de dos componentes: la pintura (parte A) y un catalizador o endurecedor (parte B). Por separado no sirven; al mezclarlos empieza una reacción química que forma una película muy dura, muy adherida y muy resistente a químicos y humedad — como una resina. Por eso se usa como capa intermedia de barrera en el acero. Sus dos debilidades: se degrada con el sol (por eso encima lleva poliuretano) y una vez mezclada tiene tiempo de vida limitado (pot-life): lo que no se aplique a tiempo, se endurece en el bote y se tira.
B11: — PELÍCULA Y ESPESORES —
B12: Película húmeda vs. película seca | C12: La película HÚMEDA (EPH o WFT) es el espesor de la pintura recién aplicada, todavía mojada: se mide en el momento con un "peine" metálico. La película SECA (EPS o DFT) es lo que queda cuando los solventes se evaporan: se mide con un aparato magnético al día siguiente. La húmeda siempre es más gruesa, porque parte del volumen es solvente que se va al aire. La relación es: espesor seco = espesor húmedo × % de sólidos. Ejemplo: si la pintura tiene 60% de sólidos y aplico 125 µm húmedas, quedarán 75 µm secas. El pintor controla con el peine EN EL MOMENTO (todavía puede corregir); el inspector mide la seca DESPUÉS (ya no hay corrección barata). Por eso el peine ahorra dinero.
B13: Conversión micra ↔ mils | C13: 1 mils = 25.4 µm | 1 µm = 0.0394 mils. Ejemplos: 2 mils = 50.8 µm | 3 mils = 76.2 µm | 5 mils = 127 µm | 10 mils = 254 µm. Truco de campo: para pasar de mils a micras, multiplique por 25 y súmele "un poquito"; para pasar de micras a mils, divida entre 25.
B14: — TIEMPOS DE LA PINTURA —
B15: Tiempo de secado | C15: Cuánto tarda la pintura en dejar de estar pegajosa. La hoja técnica da varios: "seco al tacto" (se puede tocar sin marcar), "seco para manejo" (se puede mover la pieza sin dañarla) y "curado total" (alcanzó toda su dureza; en epóxicos puede tomar 7 días). Importa para producción: mover una pieza antes del "seco para manejo" deja huellas y obliga a retocar = más pintura y más horas.
B16: Pot-life (vida útil de la mezcla) | C16: En pinturas de dos componentes, es el tiempo que tiene para APLICAR la mezcla desde que junta la parte A con la B. Puede ser de 1 a 8 horas según el producto y el calor (a más calor, menos tiempo). Pasado ese tiempo, la pintura se espesa y ya no sirve aunque se vea líquida: aplicarla es garantía de falla. Regla de oro: mezclar solo lo que se va a aplicar. Cada bote mezclado que se queda sin aplicar es dinero directo a la basura — es uno de los desperdicios más comunes y más evitables.
B17: Tiempo de repintado | C17: Es la ventana para aplicar la siguiente capa: un MÍNIMO (antes de ese tiempo la capa de abajo está muy fresca y la nueva la arruga) y un MÁXIMO (después de ese tiempo la capa de abajo quedó tan dura y lisa que la nueva no agarra; hay que lijarla primero). Pasarse del máximo cuesta caro: lijar toda la superficie es horas-hombre y consumibles no presupuestados. Planear la secuencia de capas respetando estas ventanas es tarea del supervisor.
B18: Limpiador de máquina vs. diluyente: no los confunda | C18: El DILUYENTE (thinner de aplicación) es el solvente específico que la hoja técnica autoriza para ajustar la viscosidad de la pintura y que atomice mejor: se agrega en poca cantidad (típico 5–10%) y DEBE ser el que indica el fabricante — usar otro puede arruinar la pintura. El LIMPIADOR (solvente de limpieza o flush) es más barato y agresivo: sirve para lavar bomba, mangueras y pistola al terminar o al cambiar de producto, y NUNCA debe mezclarse con la pintura. Usar limpiador como diluyente "porque es más barato" produce cráteres, mala adherencia y reclamos. Son dos garrafas distintas, con dos usos distintos.
B19: — EQUIPOS Y APLICACIÓN —
B20: Airless normal vs. equipo plural (tipo Graco XM/XP) | C20: Un AIRLESS normal bombea pintura ya mezclada a alta presión: usted junta la parte A y la B en un bote, y desde ese momento corre el pot-life. Todo lo que quede en el bote, la bomba y las mangueras al agotarse el tiempo, se tira, y hay que lavar el equipo con solvente cada vez. Un equipo PLURAL (dos componentes, como los Graco XM o XP) bombea la parte A y la parte B por mangueras SEPARADAS y las mezcla apenas unos centímetros antes de la pistola: la pintura mezclada que existe en el sistema es mínima. Resultado: prácticamente se elimina el desperdicio por pot-life, se reduce el solvente de lavado (solo se lava el tramo corto mezclado) y la proporción de mezcla es exacta siempre (sin errores humanos de dosificación). El ahorro típico en material está entre 10% y 20% del consumo, más el ahorro en solvente (hasta 70–80% menos) — y es mayor cuanto más caro es el producto y más arranques/paros tiene la jornada. En intumescentes y epóxicos de pot-life corto, el plural puede ser la diferencia entre ganar o perder dinero en la partida. Contra: inversión y mantenimiento del equipo más altos, y requiere operador capacitado.
B21: ¿Por qué importa usar la boquilla correcta? | C21: La boquilla (tip) de la pistola define dos cosas: el ANCHO del abanico y el CAUDAL de pintura. Si el abanico es más ancho que la pieza (ej. abanico de 30 cm para pintar un ángulo de 7 cm), la mayoría de la pintura pasa de largo: puro desperdicio. Si el orificio es más grande de lo que pide la hoja técnica, sale más pintura de la que la superficie puede recibir: chorreos, espesores excedidos (que también son desperdicio: cada micra de más es pintura pagada que el cliente no pidió) y repasos. Además, una boquilla DESGASTADA agranda su orificio y deforma el abanico: un tip gastado puede aumentar el consumo 20–30% sin que nadie lo note. Regla práctica: abanico angosto para piezas angostas, abanico ancho para placas; y cambiar el tip cuando el abanico "hace colas" o el patrón se redondea. Es la pieza más barata del equipo y la que más pintura puede ahorrar.
B22: Resistencia mecánica de la pintura | C22: Es la capacidad de la película para aguantar golpes, abrasión (roce), rayado y flexión sin desprenderse ni agrietarse. Se vuelve importante cuando la pieza va a sufrir maltrato: transporte al sitio (estiba, cadenas, eslingas), montaje (maniobras, tornilleo, caminado sobre las piezas) y servicio (pisos, zonas de tráfico, impacto de material). Si el sistema es "bonito pero blandito", llegará rayado a obra y el retoque en campo cuesta 3–5 veces más que pintar en taller. Al elegir el sistema hay que preguntar: ¿cuánto va a viajar y cuánto la van a golpear? En piezas de mucho manejo conviene un intermedio epóxico de alto espesor y programar el acabado final en obra, o proteger los apoyos con separadores de madera/hule al estibar.
B23: — PINTURA IGNÍFUGA (INTUMESCENTE) —
B24: ¿Qué significa el "rating" (R30, R60, R90, R120)? | C24: Es el tiempo, en MINUTOS, que la protección debe mantener el acero por debajo de su temperatura de falla durante un incendio: R60 = 60 minutos de resistencia. Lo fija el reglamento de construcción y el proyecto según el uso del edificio (más gente y más pisos = más minutos). No es una calidad de la pintura en sí: es una exigencia que se cumple con ESPESOR. El mismo producto puede dar R30 con una capa delgada o R120 con una capa muy gruesa.
B25: ¿Cómo influye el rating en la cantidad de pintura a pedir? | C25: Directamente y de forma brutal: a más minutos de rating, más espesor, y el espesor de intumescente no crece de a poquito — se multiplica. Además influye la "masividad" (Hp/A): los perfiles flacos se calientan rápido y piden aún más espesor que los robustos. Como referencia general (SIEMPRE validar contra la carta certificada del fabricante): R30 pide del orden de 250–650 µm; R60 entre 450–1,700 µm; R90 entre 900–3,500 µm; y R120 entre 1,500–6,000 µm, según qué tan esbelto sea el perfil. Compare: un sistema anticorrosivo completo son ~275 µm. Un R90 puede llevar DIEZ VECES más película que todo el sistema de pintura normal — por eso una partida con ignífugo puede costar más en pintura que toda la estructura junta, y por eso el modelo pide el Hp/A de cada perfil en la hoja 6_IGNIFUGO en lugar de usar un promedio.
B26: ¿En qué se diferencia aplicar intumescente vs. pintura normal? | C26: Con una pintura convencional o epóxica usted aplica 1 pasada de 50–125 µm y listo. Con el intumescente está construyendo una capa hasta 40 veces más gruesa: se aplica en VARIAS pasadas (cada una de máximo 400–800 µm húmedas, porque más se descuelga), esperando el secado entre pasada y pasada — proteger una columna a R90 puede tomar varios días de calendario. Exige medir el espesor pasada por pasada y registrarlo (el inspector lo pide para liberar), condiciones controladas (los de base agua no toleran lluvia ni frío antes de curar), un primario específico aprobado por el fabricante (no cualquier primario sirve) y muchas veces un sellador de acabado encima si va al exterior. En resumen: más pasadas, más control, más tiempo de ocupación de la cabina y más desperdicio — por eso la Tabla D le carga un recargo adicional del 12% que la pintura normal no lleva.
B28: — ESTIMACIÓN RÁPIDA DE ÁREA —
B29: ¿Cómo estimo los m² a pintar cuando solo tengo el tonelaje? | C29: Con el "espesor promedio" del acero del proyecto. La idea es sencilla: el acero pesa 7,850 kg por m³. Si imagina todo el acero del proyecto como una gran lámina de espesor promedio "e", esa lámina tiene dos caras que se pintan. De ahí sale la fórmula rápida: m² por tonelada ≈ 255 ÷ espesor promedio (en mm). Ejemplos: perfiles ligeros de 6 mm → 255/6 ≈ 42 m²/ton; estructura mediana de 10 mm → 25 m²/ton; estructura pesada de 20 mm → 13 m²/ton; placas gruesas de 50 mm → 5 m²/ton. Regla nemotécnica: acero flaco = mucha área por tonelada; acero gordo = poca área por tonelada. El espesor promedio del proyecto se estima ponderando: si el 70% del peso son perfiles de 9 mm y el 30% placas de 25 mm, e ≈ 0.7×9 + 0.3×25 ≈ 14 mm → 18 m²/ton.
B30: Área pintable vs. área total: no pinte lo que no se pinta | C30: La fórmula da el área TOTAL de acero, pero no todo se pinta. Hay que descontar el área NO PINTABLE: el interior de los tubos HSS cerrados (no se pinta ni se puede), las caras que quedarán embebidas o en contacto con concreto (normalmente se dejan sin pintar por adherencia), las superficies de contacto de conexiones de deslizamiento crítico (el proyecto las exige SIN pintura o con pintura certificada de fricción clase A/B), el patín superior de vigas que recibirá conectores de cortante y losa, y las caras de empalme que se sueldan en campo (se dejan sin pintar 50–100 mm alrededor de la soldadura). Según el tipo de estructura, esto puede ser del 5% al 20% del área total. El modelo lo maneja con un "% no pintable" por familia que usted calibra.
B31: ¿Para qué comparar el estimado contra el área real? | C31: Es un control de calidad del presupuesto. El estimado por tonelaje (rápido, para cotizar cuando aún no hay modelo) y el área real medida del modelo Tekla/IFC (exacta, cuando ya existe) deberían parecerse. Si difieren mucho —más de ±15% es la alarma típica— algo está mal: o el espesor promedio que supuso no corresponde al proyecto, o el reporte de áreas del modelo trae superficies no pintables incluidas (interiores de HSS, caras de contacto), o hay piezas duplicadas/faltantes en el listado. La hoja 12_ESTIMACION hace esa comparación por familia y enciende la alerta para que se reevalúen las áreas ANTES de comprar pintura o firmar la oferta. Comprar con un área inflada 20% es regalar cuñetes; cotizar con un área corta 20% es perder dinero.
B33: — ACERO NUEVO VS. ACERO VIEJO —
B34: ¿Gasta lo mismo blastear acero nuevo que viejo? | C34: No, y la diferencia es grande. La norma ISO 8501-1 clasifica cómo llega el acero en cuatro grados: A (nuevo, con la cascarilla de laminación —calamina— completa y pegada), B (nuevo pero intemperizado: la calamina empieza a soltarse), C (viejo: el óxido ya se comió la calamina) y D (viejo y picado: la corrosión dejó hoyitos —picaduras— en toda la superficie). Lo curioso: el acero A, aunque es "nuevo", NO es el más barato de blastear — la calamina es dura como vidrio y arrancarla consume ~30% más abrasivo, y además pide granalla angular (grit), porque la esférica (shot) solo la pule sin cortarla. El más barato es el B (la condición típica del perfil comercial). El C consume ~40% más por el óxido que amortigua el impacto y ensucia la granalla. Y el D casi duplica el consumo: hay que sacar el óxido del fondo de cada picadura. Por eso el modelo pregunta la condición (columna O de 7_ABRASIVO) antes de calcular el abrasivo.
B35: ¿Y afecta también al perfil de anclaje? | C35: Sí, en dos sentidos opuestos. Con acero A: si no se corta la calamina por completo, el perfil que se mide está sobre la cascarilla, no sobre el metal — y esa cascarilla se desprenderá después llevándose la pintura; hay que asegurar que el abrasivo llegue al metal base. Con acero D: las picaduras ya traen su propia rugosidad, que muchas veces es MAYOR que el perfil especificado. Eso no es gratis: un perfil más profundo significa más volumen muerto, o sea que la primera capa de primario consume más pintura para rellenar los valles (por eso en acero picado conviene usar R3/R4 en la Tabla C y medir el perfil real con cinta Testex, no asumir el de la especificación). En resumen: la condición inicial del acero mueve DOS renglones del presupuesto a la vez — el abrasivo y el primario.

Sheet 10_PIEZAS
B2: LISTADO DE PIEZAS — ÁREA Y PESO POR PIEZA Y FAMILIA
B3: Pegue aquí el reporte de Tekla / IFC (marca, familia, cantidad, área y peso unitarios). Si tiene el archivo de exportación (Excel, CSV o IFC), Claude puede leerlo y llenar esta tabla por usted. El costo de aplicación por pieza se toma del APU de su familia (hoja 11_APU).
B5: Marca / Pieza | C5: Descripción | D5: Familia | E5: Cant | F5: Área unit (m²) | G5: Peso unit (kg) | H5: Área total (m²) | I5: Peso total (kg) | J5: $/m² aplicado (familia) | K5: Costo pintura pieza ($) | L5: $/kg pieza
B6: C-101 | C6: Columna W12x65 h=6.0 m | D6: COLUMNA | E6: 8 | F6: 8.9 | G6: 580 | H6: =IF($B6="","",E6*F6) -> 71.2 | I6: =IF($B6="","",E6*G6) -> 4640 | J6: =IF($B6="","",VLOOKUP(D6,'11_APU'!$B$7:$P$12,14,0)) -> 19.6875 | K6: =IF($B6="","",H6*J6) -> 1401.75 | L6: =IF(OR($B6="",I6=0),"",K6/I6) -> 0.30210129
B7: C-201 | C7: Columna W14x90 ignífuga | D7: COLUMNA | E7: 6 | F7: 10.5 | G7: 810 | H7: =IF($B7="","",E7*F7) -> 63 | I7: =IF($B7="","",E7*G7) -> 4860 | J7: =IF($B7="","",VLOOKUP(D7,'11_APU'!$B$7:$P$12,14,0)) -> 19.6875 | K7: =IF($B7="","",H7*J7) -> 1240.3125 | L7: =IF(OR($B7="",I7=0),"",K7/I7) -> 0.25520833
B8: V-301 | C8: Viga W24x76 L=9.0 m | D8: VIGA | E8: 24 | F8: 16.2 | G8: 1030 | H8: =IF($B8="","",E8*F8) -> 388.8 | I8: =IF($B8="","",E8*G8) -> 24720 | J8: =IF($B8="","",VLOOKUP(D8,'11_APU'!$B$7:$P$12,14,0)) -> 16.875 | K8: =IF($B8="","",H8*J8) -> 6561 | L8: =IF(OR($B8="",I8=0),"",K8/I8) -> 0.26541262
B9: V-401 | C9: Viga W16x40 L=7.5 m | D9: VIGA | E9: 30 | F9: 9.8 | G9: 447 | H9: =IF($B9="","",E9*F9) -> 294 | I9: =IF($B9="","",E9*G9) -> 13410 | J9: =IF($B9="","",VLOOKUP(D9,'11_APU'!$B$7:$P$12,14,0)) -> 16.875 | K9: =IF($B9="","",H9*J9) -> 4961.25 | L9: =IF(OR($B9="",I9=0),"",K9/I9) -> 0.36996644
B10: A-501 | C10: Armadura cubierta 18 m | D10: CELOSIA | E10: 10 | F10: 42 | G10: 1650 | H10: =IF($B10="","",E10*F10) -> 420 | I10: =IF($B10="","",E10*G10) -> 16500 | J10: =IF($B10="","",VLOOKUP(D10,'11_APU'!$B$7:$P$12,14,0)) -> 30.9375 | K10: =IF($B10="","",H10*J10) -> 12993.75 | L10: =IF(OR($B10="",I10=0),"",K10/I10) -> 0.7875
B11: CV-601 | C11: Contraventeo HSS 4x4 | D11: CONTRAVENTEO | E11: 16 | F11: 3.1 | G11: 155 | H11: =IF($B11="","",E11*F11) -> 49.6 | I11: =IF($B11="","",E11*G11) -> 2480 | J11: =IF($B11="","",VLOOKUP(D11,'11_APU'!$B$7:$P$12,14,0)) -> 19.6875 | K11: =IF($B11="","",H11*J11) -> 976.5 | L11: =IF(OR($B11="",I11=0),"",K11/I11) -> 0.39375
B12: ESC-701 | C12: Escalera marina + guarda | D12: MISCELANEO | E12: 4 | F12: 12.4 | G12: 380 | H12: =IF($B12="","",E12*F12) -> 49.6 | I12: =IF($B12="","",E12*G12) -> 1520 | J12: =IF($B12="","",VLOOKUP(D12,'11_APU'!$B$7:$P$12,14,0)) -> 28.125 | K12: =IF($B12="","",H12*J12) -> 1395 | L12: =IF(OR($B12="",I12=0),"",K12/I12) -> 0.91776316
B13: PL-801 | C13: Placas base 50 mm | D13: PLACA | E13: 14 | F13: 0.9 | G13: 118 | H13: =IF($B13="","",E13*F13) -> 12.6 | I13: =IF($B13="","",E13*G13) -> 1652 | J13: =IF($B13="","",VLOOKUP(D13,'11_APU'!$B$7:$P$12,14,0)) -> 11.25 | K13: =IF($B13="","",H13*J13) -> 141.75 | L13: =IF(OR($B13="",I13=0),"",K13/I13) -> 0.085805085
H14: =IF($B14="","",E14*F14) | I14: =IF($B14="","",E14*G14) | J14: =IF($B14="","",VLOOKUP(D14,'11_APU'!$B$7:$P$12,14,0)) | K14: =IF($B14="","",H14*J14) | L14: =IF(OR($B14="",I14=0),"",K14/I14)
H15: =IF($B15="","",E15*F15) | I15: =IF($B15="","",E15*G15) | J15: =IF($B15="","",VLOOKUP(D15,'11_APU'!$B$7:$P$12,14,0)) | K15: =IF($B15="","",H15*J15) | L15: =IF(OR($B15="",I15=0),"",K15/I15)
H16: =IF($B16="","",E16*F16) | I16: =IF($B16="","",E16*G16) | J16: =IF($B16="","",VLOOKUP(D16,'11_APU'!$B$7:$P$12,14,0)) | K16: =IF($B16="","",H16*J16) | L16: =IF(OR($B16="",I16=0),"",K16/I16)
H17: =IF($B17="","",E17*F17) | I17: =IF($B17="","",E17*G17) | J17: =IF($B17="","",VLOOKUP(D17,'11_APU'!$B$7:$P$12,14,0)) | K17: =IF($B17="","",H17*J17) | L17: =IF(OR($B17="",I17=0),"",K17/I17)
H18: =IF($B18="","",E18*F18) | I18: =IF($B18="","",E18*G18) | J18: =IF($B18="","",VLOOKUP(D18,'11_APU'!$B$7:$P$12,14,0)) | K18: =IF($B18="","",H18*J18) | L18: =IF(OR($B18="",I18=0),"",K18/I18)
H19: =IF($B19="","",E19*F19) | I19: =IF($B19="","",E19*G19) | J19: =IF($B19="","",VLOOKUP(D19,'11_APU'!$B$7:$P$12,14,0)) | K19: =IF($B19="","",H19*J19) | L19: =IF(OR($B19="",I19=0),"",K19/I19)
H20: =IF($B20="","",E20*F20) | I20: =IF($B20="","",E20*G20) | J20: =IF($B20="","",VLOOKUP(D20,'11_APU'!$B$7:$P$12,14,0)) | K20: =IF($B20="","",H20*J20) | L20: =IF(OR($B20="",I20=0),"",K20/I20)
H21: =IF($B21="","",E21*F21) | I21: =IF($B21="","",E21*G21) | J21: =IF($B21="","",VLOOKUP(D21,'11_APU'!$B$7:$P$12,14,0)) | K21: =IF($B21="","",H21*J21) | L21: =IF(OR($B21="",I21=0),"",K21/I21)
H22: =IF($B22="","",E22*F22) | I22: =IF($B22="","",E22*G22) | J22: =IF($B22="","",VLOOKUP(D22,'11_APU'!$B$7:$P$12,14,0)) | K22: =IF($B22="","",H22*J22) | L22: =IF(OR($B22="",I22=0),"",K22/I22)
H23: =IF($B23="","",E23*F23) | I23: =IF($B23="","",E23*G23) | J23: =IF($B23="","",VLOOKUP(D23,'11_APU'!$B$7:$P$12,14,0)) | K23: =IF($B23="","",H23*J23) | L23: =IF(OR($B23="",I23=0),"",K23/I23)
H24: =IF($B24="","",E24*F24) | I24: =IF($B24="","",E24*G24) | J24: =IF($B24="","",VLOOKUP(D24,'11_APU'!$B$7:$P$12,14,0)) | K24: =IF($B24="","",H24*J24) | L24: =IF(OR($B24="",I24=0),"",K24/I24)
H25: =IF($B25="","",E25*F25) | I25: =IF($B25="","",E25*G25) | J25: =IF($B25="","",VLOOKUP(D25,'11_APU'!$B$7:$P$12,14,0)) | K25: =IF($B25="","",H25*J25) | L25: =IF(OR($B25="",I25=0),"",K25/I25)
... H35: =IF($B35="","",E35*F35) | I35: =IF($B35="","",E35*G35) | J35: =IF($B35="","",VLOOKUP(D35,'11_APU'!$B$7:$P$12,14,0)) | K35: =IF($B35="","",H35*J35) | L35: =IF(OR($B35="",I35=0),"",K35/I35)
C36: TOTALES | H36: =SUM(H6:H35) -> 1348.8 | I36: =SUM(I6:I35) -> 69782 | K36: =SUM(K6:K35) -> 29671.312 | L36: =IF(I36=0,"",K36/I36) -> 0.42520009

Sheet 11_APU
B2: APU — ANÁLISIS DE PRECIO UNITARIO DE PINTURA POR FAMILIA (POR m² O POR kg)
B3: El APU descompone el costo de la aplicación de pintura en materiales, mano de obra, equipo e indirectos. Elija la UNIDAD de venta por familia (m² o kg): el PU final sale en esa unidad. La conversión m²↔kg usa el ratio real de las piezas capturadas en 10_PIEZAS.
B5: Referencia sugerida material (proyecto completo): | F5: =IF('10_PIEZAS'!H36=0,"",'5_RESUMEN'!L14/'10_PIEZAS'!H36) -> 0 | G5: $/m² pintura | H5: =IF('10_PIEZAS'!H36=0,"",'7_ABRASIVO'!N29/'10_PIEZAS'!H36) -> 0 | I5: $/m² abrasivo | L5: Cópielas como punto de partida en las columnas azules E y F, y ajuste por familia.
B6: Familia | C6: Unidad (m2/kg) | D6: Área (m²) | E6: Peso (kg) | F6: kg/m² | G6: Mat. pintura ($/m²) | H6: Abrasivo ($/m²) | I6: MO (HH/m²) | J6: Tarifa ($/HH) | K6: MO ($/m²) | L6: Equipo ($/m²) | M6: Subtotal ($/m²) | N6: % Indir.+ Util. | O6: PU ($/m²) | P6: PU ($/kg) | Q6: PU EN UNIDAD ELEGIDA
B7: COLUMNA | C7: m2 | D7: =SUMIF('10_PIEZAS'!$D$6:$D$35,$B7,'10_PIEZAS'!$H$6:$H$35) -> 134.2 | E7: =SUMIF('10_PIEZAS'!$D$6:$D$35,$B7,'10_PIEZAS'!$I$6:$I$35) -> 9500 | F7: =IF(D7=0,"",E7/D7) -> 70.789866 | G7: 0 | H7: 0 | I7: 0.35 | J7: 45 | K7: =I7*J7 -> 15.75 | L7: 0 | M7: =G7+H7+K7+L7 -> 15.75 | N7: 0.25 | O7: =M7*(1+N7) -> 19.6875 | P7: =IF(OR(F7="",F7=0),"",O7/F7) -> 0.27811184 | Q7: =IF(C7="kg",IF(P7="","",P7),O7) -> 19.6875
B8: VIGA | C8: m2 | D8: =SUMIF('10_PIEZAS'!$D$6:$D$35,$B8,'10_PIEZAS'!$H$6:$H$35) -> 682.8 | E8: =SUMIF('10_PIEZAS'!$D$6:$D$35,$B8,'10_PIEZAS'!$I$6:$I$35) -> 38130 | F8: =IF(D8=0,"",E8/D8) -> 55.843585 | G8: 0 | H8: 0 | I8: 0.3 | J8: 45 | K8: =I8*J8 -> 13.5 | L8: 0 | M8: =G8+H8+K8+L8 -> 13.5 | N8: 0.25 | O8: =M8*(1+N8) -> 16.875 | P8: =IF(OR(F8="",F8=0),"",O8/F8) -> 0.30218332 | Q8: =IF(C8="kg",IF(P8="","",P8),O8) -> 16.875
B9: CELOSIA | C9: m2 | D9: =SUMIF('10_PIEZAS'!$D$6:$D$35,$B9,'10_PIEZAS'!$H$6:$H$35) -> 420 | E9: =SUMIF('10_PIEZAS'!$D$6:$D$35,$B9,'10_PIEZAS'!$I$6:$I$35) -> 16500 | F9: =IF(D9=0,"",E9/D9) -> 39.285714 | G9: 0 | H9: 0 | I9: 0.55 | J9: 45 | K9: =I9*J9 -> 24.75 | L9: 0 | M9: =G9+H9+K9+L9 -> 24.75 | N9: 0.25 | O9: =M9*(1+N9) -> 30.9375 | P9: =IF(OR(F9="",F9=0),"",O9/F9) -> 0.7875 | Q9: =IF(C9="kg",IF(P9="","",P9),O9) -> 30.9375
B10: CONTRAVENTEO | C10: kg | D10: =SUMIF('10_PIEZAS'!$D$6:$D$35,$B10,'10_PIEZAS'!$H$6:$H$35) -> 49.6 | E10: =SUMIF('10_PIEZAS'!$D$6:$D$35,$B10,'10_PIEZAS'!$I$6:$I$35) -> 2480 | F10: =IF(D10=0,"",E10/D10) -> 50 | G10: 0 | H10: 0 | I10: 0.35 | J10: 45 | K10: =I10*J10 -> 15.75 | L10: 0 | M10: =G10+H10+K10+L10 -> 15.75 | N10: 0.25 | O10: =M10*(1+N10) -> 19.6875 | P10: =IF(OR(F10="",F10=0),"",O10/F10) -> 0.39375 | Q10: =IF(C10="kg",IF(P10="","",P10),O10) -> 0.39375
B11: MISCELANEO | C11: kg | D11: =SUMIF('10_PIEZAS'!$D$6:$D$35,$B11,'10_PIEZAS'!$H$6:$H$35) -> 49.6 | E11: =SUMIF('10_PIEZAS'!$D$6:$D$35,$B11,'10_PIEZAS'!$I$6:$I$35) -> 1520 | F11: =IF(D11=0,"",E11/D11) -> 30.645161 | G11: 0 | H11: 0 | I11: 0.5 | J11: 45 | K11: =I11*J11 -> 22.5 | L11: 0 | M11: =G11+H11+K11+L11 -> 22.5 | N11: 0.25 | O11: =M11*(1+N11) -> 28.125 | P11: =IF(OR(F11="",F11=0),"",O11/F11) -> 0.91776316 | Q11: =IF(C11="kg",IF(P11="","",P11),O11) -> 0.91776316
B12: PLACA | C12: m2 | D12: =SUMIF('10_PIEZAS'!$D$6:$D$35,$B12,'10_PIEZAS'!$H$6:$H$35) -> 12.6 | E12: =SUMIF('10_PIEZAS'!$D$6:$D$35,$B12,'10_PIEZAS'!$I$6:$I$35) -> 1652 | F12: =IF(D12=0,"",E12/D12) -> 131.11111 | G12: 0 | H12: 0 | I12: 0.2 | J12: 45 | K12: =I12*J12 -> 9 | L12: 0 | M12: =G12+H12+K12+L12 -> 9 | N12: 0.25 | O12: =M12*(1+N12) -> 11.25 | P12: =IF(OR(F12="",F12=0),"",O12/F12) -> 0.085805085 | Q12: =IF(C12="kg",IF(P12="","",P12),O12) -> 11.25
B14: Notas: MO (HH/m²) incluye blasteo manual/carga de máquina + aplicación + retoques; calíbrela con los HH reales de planta por familia (misma lógica HH/ton del motor de presupuesto, pero en m²). "Equipo" = depreciación/renta de granalladora, compresor, equipo airless o plural, prorrateada por m². "% Indir.+Util." = indirectos de planta + utilidad según política comercial vigente. El PU por kg divide el PU por m² entre el ratio kg/m² real de la familia: por eso una celosía (poca masa, mucha área) es cara por kg y una placa es barata por kg.

Sheet 12_ESTIMACION
B2: ESTIMACIÓN DE m² PINTABLES POR ESPESOR PROMEDIO vs. ÁREA REAL DEL MODELO
B3: Método: m²/ton ≈ 255 / espesor promedio (mm), menos el % de área no pintable. El peso por familia viene de 10_PIEZAS. Si la diferencia contra el área real del modelo supera la tolerancia, la fila enciende REEVALUAR: revise espesor promedio supuesto, superficies no pintables incluidas en el reporte del modelo, o piezas duplicadas/faltantes.
B5: Tolerancia de alerta (±): | C5: 0.15 | D5: Diferencias mayores a esta tolerancia (en cualquier sentido) marcan REEVALUAR.
B7: Familia | C7: Peso (ton) | D7: Espesor prom. (mm) | E7: m²/ton (=255/e) | F7: % área NO pintable | G7: m² estimados pintables | H7: m² reales (modelo) | I7: Diferencia (m²) | J7: Dif. (%) | K7: Veredicto | L7: Guía de revisión si marca REEVALUAR
B8: COLUMNA | C8: =SUMIF('10_PIEZAS'!$D$6:$D$35,$B8,'10_PIEZAS'!$I$6:$I$35)/1000 -> 9.5 | D8: 14 | E8: =IF(D8=0,"",255/D8) -> 18.214286 | F8: 0.08 | G8: =IF(D8=0,"",C8*E8*(1-F8)) -> 159.19286 | H8: =SUMIF('10_PIEZAS'!$D$6:$D$35,$B8,'10_PIEZAS'!$H$6:$H$35) -> 134.2 | I8: =IF(OR(G8="",H8=0),"",H8-G8) -> -24.992857 | J8: =IF(OR(G8="",G8=0,H8=0),"",(H8-G8)/G8) -> -0.15699735 | K8: =IF(J8="","SIN DATOS",IF(ABS(J8)>$C$5,"⚠ REEVALUAR","OK")) -> ⚠ REEVALUAR | L8: Caras embebidas en dados/placas base; zonas sin pintar de empalmes de campo.
B9: VIGA | C9: =SUMIF('10_PIEZAS'!$D$6:$D$35,$B9,'10_PIEZAS'!$I$6:$I$35)/1000 -> 38.13 | D9: 11 | E9: =IF(D9=0,"",255/D9) -> 23.181818 | F9: 0.1 | G9: =IF(D9=0,"",C9*E9*(1-F9)) -> 795.53045 | H9: =SUMIF('10_PIEZAS'!$D$6:$D$35,$B9,'10_PIEZAS'!$H$6:$H$35) -> 682.8 | I9: =IF(OR(G9="",H9=0),"",H9-G9) -> -112.73045 | J9: =IF(OR(G9="",G9=0,H9=0),"",(H9-G9)/G9) -> -0.14170476 | K9: =IF(J9="","SIN DATOS",IF(ABS(J9)>$C$5,"⚠ REEVALUAR","OK")) -> OK | L9: Patín superior con conectores de cortante bajo losa; superficies slip-critical.
B10: CELOSIA | C10: =SUMIF('10_PIEZAS'!$D$6:$D$35,$B10,'10_PIEZAS'!$I$6:$I$35)/1000 -> 16.5 | D10: 7 | E10: =IF(D10=0,"",255/D10) -> 36.428571 | F10: 0.05 | G10: =IF(D10=0,"",C10*E10*(1-F10)) -> 571.01786 | H10: =SUMIF('10_PIEZAS'!$D$6:$D$35,$B10,'10_PIEZAS'!$H$6:$H$35) -> 420 | I10: =IF(OR(G10="",H10=0),"",H10-G10) -> -151.01786 | J10: =IF(OR(G10="",G10=0,H10=0),"",(H10-G10)/G10) -> -0.26447134 | K10: =IF(J10="","SIN DATOS",IF(ABS(J10)>$C$5,"⚠ REEVALUAR","OK")) -> ⚠ REEVALUAR | L10: Cuerdas/diagonales casi todo pintable; verificar que el modelo no duplique caras de placas de nudo.
B11: CONTRAVENTEO | C11: =SUMIF('10_PIEZAS'!$D$6:$D$35,$B11,'10_PIEZAS'!$I$6:$I$35)/1000 -> 2.48 | D11: 8 | E11: =IF(D11=0,"",255/D11) -> 31.875 | F11: 0.15 | G11: =IF(D11=0,"",C11*E11*(1-F11)) -> 67.1925 | H11: =SUMIF('10_PIEZAS'!$D$6:$D$35,$B11,'10_PIEZAS'!$H$6:$H$35) -> 49.6 | I11: =IF(OR(G11="",H11=0),"",H11-G11) -> -17.5925 | J11: =IF(OR(G11="",G11=0,H11=0),"",(H11-G11)/G11) -> -0.26182238 | K11: =IF(J11="","SIN DATOS",IF(ABS(J11)>$C$5,"⚠ REEVALUAR","OK")) -> ⚠ REEVALUAR | L11: HSS cerrados: el interior NO es pintable — verifique que el reporte del modelo no lo incluya.
B12: MISCELANEO | C12: =SUMIF('10_PIEZAS'!$D$6:$D$35,$B12,'10_PIEZAS'!$I$6:$I$35)/1000 -> 1.52 | D12: 6 | E12: =IF(D12=0,"",255/D12) -> 42.5 | F12: 0.05 | G12: =IF(D12=0,"",C12*E12*(1-F12)) -> 61.37 | H12: =SUMIF('10_PIEZAS'!$D$6:$D$35,$B12,'10_PIEZAS'!$H$6:$H$35) -> 49.6 | I12: =IF(OR(G12="",H12=0),"",H12-G12) -> -11.77 | J12: =IF(OR(G12="",G12=0,H12=0),"",(H12-G12)/G12) -> -0.19178752 | K12: =IF(J12="","SIN DATOS",IF(ABS(J12)>$C$5,"⚠ REEVALUAR","OK")) -> ⚠ REEVALUAR | L12: Escaleras/barandal casi todo pintable; rejilla galvanizada NO se pinta (excluirla del listado).
B13: PLACA | C13: =SUMIF('10_PIEZAS'!$D$6:$D$35,$B13,'10_PIEZAS'!$I$6:$I$35)/1000 -> 1.652 | D13: 38 | E13: =IF(D13=0,"",255/D13) -> 6.7105263 | F13: 0.2 | G13: =IF(D13=0,"",C13*E13*(1-F13)) -> 8.8686316 | H13: =SUMIF('10_PIEZAS'!$D$6:$D$35,$B13,'10_PIEZAS'!$H$6:$H$35) -> 12.6 | I13: =IF(OR(G13="",H13=0),"",H13-G13) -> 3.7313684 | J13: =IF(OR(G13="",G13=0,H13=0),"",(H13-G13)/G13) -> 0.42073779 | K13: =IF(J13="","SIN DATOS",IF(ABS(J13)>$C$5,"⚠ REEVALUAR","OK")) -> ⚠ REEVALUAR | L13: Caras de contacto con concreto y superficies de fricción de conexiones: usualmente sin pintura.
B14: TOTAL | C14: =SUM(C8:C13) -> 69.782 | G14: =SUM(G8:G13) -> 1663.1723 | H14: =SUM(H8:H13) -> 1348.8 | I14: =SUM(I8:I13) -> -314.3723 | J14: =IF(OR(G14=0,H14=0),"",(H14-G14)/G14) -> -0.18901968 | K14: =IF(J14="","",IF(ABS(J14)>$C$5,"⚠ REEVALUAR","OK")) -> ⚠ REEVALUAR
B16: Uso en dos momentos: (1) EN COTIZACIÓN, cuando aún no hay modelo: use solo las columnas de estimación (capture el peso estimado directamente si no hay piezas en 10_PIEZAS) para dimensionar pintura y abrasivo. (2) EN INGENIERÍA, cuando llega el modelo Tekla/IFC: llene 10_PIEZAS con el reporte de áreas PINTABLES y esta hoja valida automáticamente. Recuerde: el reporte estándar de Tekla suele traer área TOTAL de las piezas; pida el reporte con las caras no pintables excluidas o descuéntelas con la columna F.

Sheet 14_INTERFAZ_MOTOR
B2: INTERFAZ PARA EL MOTOR IFC / MOTOR DE PRESUPUESTO (lectura y escritura programática)
B3: Contrato de datos para integrar este módulo al Motor Generador IFC (ifcopenshell / Python / n8n / Claude API): el motor ESCRIBE en los rangos de entrada y LEE las salidas del bloque OUTPUT (columna C, siempre valores tras recalcular). Recalcular con LibreOffice headless o abrir/guardar en Excel antes de leer. Los nombres definidos (OUT_*) permiten leer sin depender de la posición de celda.
B5: RANGOS DE ENTRADA (el motor escribe aquí)
B6: Campo | C6: Rango destino | D6: Dir. | E6: Contenido esperado
B7: Catálogo de productos (TDS) | C7: '2_HOJA_TECNICA'!B6:L13 | D7: IN | E7: Por fila: ID, nombre, fabricante, tipo, %SV (decimal), EPS min/recom/max (µm), litros por cuñete, intumescente (SI/NO), precio por cuñete. Máx. 8 productos.
B8: Listado de piezas (del IFC) | C8: '10_PIEZAS'!B6:G35 | D8: IN | E8: Por fila: marca, descripción, familia (COLUMNA/VIGA/CELOSIA/CONTRAVENTEO/MISCELANEO/PLACA), cantidad, área pintable unitaria (m²), peso unitario (kg). Del reporte ifcopenshell: excluir caras no pintables antes de escribir.
B9: Partidas de pintura por capa | C9: '4_CALCULO'!B6:K25 | D9: IN | E9: Por fila: partida, descripción, área (m²), forma F1-F7, ambiente A1-A6, perfil R0-R4, n° capa, ID producto, EPS de la capa (µm), franjeo SI/NO. Intumescente: escribir 2 filas (planta=A1, sitio=A4/A6) repartiendo el EPS.
B10: Partidas de abrasivo | C10: '7_ABRASIVO'!B14:F28 + O14:O28 | D10: IN | E10: Por fila: partida, descripción, área (m²), abrasivo AB1-AB3, grado SP6/SP10/SP5; y en col O la condición inicial del acero A/B/C/D (vacío = B). Del IFC/inspección de patio.
B11: Espesor promedio y % no pintable | C11: '12_ESTIMACION'!D8:F13 | D11: IN | E11: Por familia: espesor promedio (mm) en col D y % no pintable (decimal) en col F. Solo necesario en modo estimación sin modelo.
B12: Precios de abrasivo | C12: '7_ABRASIVO'!I7:J9 | D12: IN | E12: Presentación (kg) y precio ($) por tipo de abrasivo.
B13: Parámetros APU por familia | C13: '11_APU'!C7:N12 | D13: IN | E13: Unidad (m2/kg), material $/m², abrasivo $/m², HH/m², tarifa, equipo $/m², % indirectos. No escribir columnas D,E,F,K,M,O,P,Q (fórmulas).
B15: BLOQUE OUTPUT (el motor lee la columna C; nombres definidos entre paréntesis)
B16: Salida | C16: Valor | D16: Unidad | E16: Nombre definido
B17: Área pintable total | C17: ='10_PIEZAS'!H36 -> 1348.8 | D17: m² | E17: OUT_AREA_M2
B18: Peso total | C18: ='10_PIEZAS'!I36 -> 69782 | D18: kg | E18: OUT_PESO_KG
B19: Litros teóricos de pintura | C19: ='4_CALCULO'!N26 -> 1782.418 | D19: L | E19: OUT_LITROS_TEORICOS
B20: Litros prácticos de pintura | C20: ='4_CALCULO'!P26 -> 2704.9836 | D20: L | E20: OUT_LITROS_PRACTICOS
B21: Litros de desperdicio | C21: ='4_CALCULO'!Q26 -> 922.56554 | D21: L | E21: OUT_LITROS_DESPERDICIO
B22: Cuñetes totales a comprar | C22: ='5_RESUMEN'!I14 -> 127 | D22: pza | E22: OUT_CUNETES
B23: Costo compra pintura | C23: ='5_RESUMEN'!L14 -> 0 | D23: $ | E23: OUT_COSTO_PINTURA
B24: Kg de abrasivo a comprar | C24: ='7_ABRASIVO'!M29 -> 3650 | D24: kg | E24: OUT_KG_ABRASIVO
B25: Costo compra abrasivo | C25: ='7_ABRASIVO'!N29 -> 0 | D25: $ | E25: OUT_COSTO_ABRASIVO
B26: Costo total de aplicación (APU) | C26: ='10_PIEZAS'!K36 -> 29671.312 | D26: $ | E26: OUT_COSTO_APLICACION
B27: Costo promedio por m² | C27: =IF('10_PIEZAS'!H36=0,"",'10_PIEZAS'!K36/'10_PIEZAS'!H36) -> 21.998304 | D27: $/m² | E27: OUT_COSTO_M2
B28: Costo promedio por kg | C28: ='10_PIEZAS'!L36 -> 0.42520009 | D28: $/kg | E28: OUT_COSTO_KG
B29: Familias con alerta de área | C29: =COUNTIF('12_ESTIMACION'!K8:K13,"⚠ REEVALUAR") -> 5 | D29: n | E29: OUT_ALERTAS_AREA
B31: PU POR FAMILIA (para el APU del presupuesto general)
B32: Familia | C32: PU en unidad elegida | D32: Unidad | E32: Nombre definido
B33: COLUMNA | C33: ='11_APU'!Q7 -> 19.6875 | D33: ='11_APU'!C7 -> m2 | E33: OUT_PU_COLUMNA
B34: VIGA | C34: ='11_APU'!Q8 -> 16.875 | D34: ='11_APU'!C8 -> m2 | E34: OUT_PU_VIGA
B35: CELOSIA | C35: ='11_APU'!Q9 -> 30.9375 | D35: ='11_APU'!C9 -> m2 | E35: OUT_PU_CELOSIA
B36: CONTRAVENTEO | C36: ='11_APU'!Q10 -> 0.39375 | D36: ='11_APU'!C10 -> kg | E36: OUT_PU_CONTRAVENTEO
B37: MISCELANEO | C37: ='11_APU'!Q11 -> 0.91776316 | D37: ='11_APU'!C11 -> kg | E37: OUT_PU_MISCELANEO
B38: PLACA | C38: ='11_APU'!Q12 -> 11.25 | D38: ='11_APU'!C12 -> m2 | E38: OUT_PU_PLACA
B40: Ejemplo de lectura en Python (openpyxl): wb = load_workbook(ruta, data_only=True); litros = wb.defined_names["OUT_LITROS_PRACTICOS"] → destino → celda.value. Ejemplo de escritura: escribir directamente en los rangos IN, guardar, recalcular con "soffice --headless --convert-to xlsx" o con el script recalc del motor, y volver a leer los OUT.
